{"v":"5.7.3","fr":60,"ip":0,"op":523,"w":856,"h":650,"nm":"jammy g 2","ddd":0,"assets":[{"id":"comp_0","layers":[{"ddd":0,"ind":1,"ty":4,"nm":"Shape Layer 1","sr":1,"ks":{"o":{"a":1,"k":[{"i":{"x":[0.833],"y":[1]},"o":{"x":[0.167],"y":[0]},"t":35,"s":[1]},{"i":{"x":[0.833],"y":[1]},"o":{"x":[0.333],"y":[0]},"t":63,"s":[20]},{"i":{"x":[0.667],"y":[1]},"o":{"x":[0.333],"y":[0]},"t":189,"s":[20]},{"i":{"x":[0.833],"y":[1]},"o":{"x":[0.167],"y":[0]},"t":215,"s":[0]},{"i":{"x":[0.833],"y":[1]},"o":{"x":[0.167],"y":[0]},"t":265,"s":[1]},{"i":{"x":[0.833],"y":[1]},"o":{"x":[0.333],"y":[0]},"t":293,"s":[20]},{"i":{"x":[0.667],"y":[1]},"o":{"x":[0.333],"y":[0]},"t":419,"s":[20]},{"t":445,"s":[0]}],"ix":11},"r":{"a":0,"k":0,"ix":10},"p":{"a":0,"k":[907.883,669.059,0],"ix":2},"a":{"a":0,"k":[-93.727,176.17,0],"ix":1},"s":{"a":1,"k":[{"i":{"x":[0.119,0.119,0.667],"y":[0.908,0.908,1]},"o":{"x":[0.299,0.299,0.333],"y":[0,0,0]},"t":35,"s":[0,0,100]},{"i":{"x":[0.119,0.119,0.667],"y":[1,1,1]},"o":{"x":[0.167,0.167,0.167],"y":[0,0,0]},"t":63,"s":[1870,1870,100]},{"i":{"x":[0.833,0.833,0.833],"y":[1,1,1]},"o":{"x":[0.167,0.167,0.167],"y":[0,0,0]},"t":189,"s":[1870,1870,100]},{"i":{"x":[0.833,0.833,0.833],"y":[1,1,1]},"o":{"x":[0.167,0.167,0.167],"y":[0,0,0]},"t":215,"s":[0,0,100]},{"i":{"x":[0.119,0.119,0.667],"y":[0.908,0.908,1]},"o":{"x":[0.299,0.299,0.333],"y":[0,0,0]},"t":265,"s":[0,0,100]},{"i":{"x":[0.119,0.119,0.667],"y":[1,1,1]},"o":{"x":[0.167,0.167,0.167],"y":[0,0,0]},"t":293,"s":[1870,1870,100]},{"i":{"x":[0.833,0.833,0.833],"y":[1,1,1]},"o":{"x":[0.167,0.167,0.167],"y":[0,0,0]},"t":419,"s":[1870,1870,100]},{"t":445,"s":[0,0,100]}],"ix":6}},"ao":0,"shapes":[{"ty":"gr","it":[{"d":1,"ty":"el","s":{"a":0,"k":[8.597,8.597],"ix":2},"p":{"a":0,"k":[0,0],"ix":3},"nm":"Ellipse Path 1","mn":"ADBE Vector Shape - Ellipse","hd":false},{"ty":"fl","c":{"a":1,"k":[{"i":{"x":[0.833],"y":[0.833]},"o":{"x":[0.167],"y":[0.167]},"t":215,"s":[1,0,1,1]},{"t":265,"s":[0,0.336764782667,1,1]}],"ix":4},"o":{"a":0,"k":100,"ix":5},"r":1,"bm":0,"nm":"Fill 1","mn":"ADBE Vector Graphic - Fill","hd":false},{"ty":"tr","p":{"a":0,"k":[-93.727,176.17],"ix":2},"a":{"a":0,"k":[0,0],"ix":1},"s":{"a":0,"k":[100,100],"ix":3},"r":{"a":0,"k":0,"ix":6},"o":{"a":0,"k":100,"ix":7},"sk":{"a":0,"k":0,"ix":4},"sa":{"a":0,"k":0,"ix":5},"nm":"Transform"}],"nm":"Ellipse 1","np":3,"cix":2,"bm":0,"ix":1,"mn":"ADBE Vector Group","hd":false}],"ip":0,"op":1200,"st":0,"bm":0},{"ddd":0,"ind":2,"ty":4,"nm":"Layer 2 Outlines","sr":1,"ks":{"o":{"a":0,"k":100,"ix":11},"r":{"a":0,"k":0,"ix":10},"p":{"a":0,"k":[1318.508,665.852,0],"ix":2},"a":{"a":0,"k":[270.189,100.68,0],"ix":1},"s":{"a":0,"k":[100,100,100],"ix":6}},"ao":0,"shapes":[{"ty":"gr","it":[{"ind":0,"ty":"sh","ix":1,"ks":{"a":0,"k":{"i":[[0,0],[0,0],[0,0],[0,0],[0,0]],"o":[[0,0],[0,0],[0,0],[0,0],[0,0]],"v":[[-268.939,-95.791],[-262.461,-99.43],[-242.953,-95.791],[13.436,3.436],[268.939,99.43]],"c":false},"ix":2},"nm":"Path 1","mn":"ADBE Vector Shape - Group","hd":false},{"ty":"st","c":{"a":0,"k":[0.361000001197,0.361000001197,0.426999978458,1],"ix":3},"o":{"a":0,"k":100,"ix":4},"w":{"a":0,"k":0.5,"ix":5},"lc":1,"lj":1,"ml":10,"bm":0,"nm":"Stroke 1","mn":"ADBE Vector Graphic - Stroke","hd":false},{"ty":"tr","p":{"a":0,"k":[270.189,100.68],"ix":2},"a":{"a":0,"k":[0,0],"ix":1},"s":{"a":0,"k":[100,100],"ix":3},"r":{"a":0,"k":0,"ix":6},"o":{"a":0,"k":100,"ix":7},"sk":{"a":0,"k":0,"ix":4},"sa":{"a":0,"k":0,"ix":5},"nm":"Transform"}],"nm":"Group 1","np":2,"cix":2,"bm":0,"ix":1,"mn":"ADBE Vector Group","hd":false}],"ip":0,"op":1200,"st":0,"bm":0},{"ddd":0,"ind":3,"ty":4,"nm":"Layer 3 Outlines","sr":1,"ks":{"o":{"a":0,"k":100,"ix":11},"r":{"a":0,"k":0,"ix":10},"p":{"a":0,"k":[583.377,341.441,0],"ix":2},"a":{"a":0,"k":[271.762,139.682,0],"ix":1},"s":{"a":0,"k":[100,100,100],"ix":6}},"ao":0,"shapes":[{"ty":"gr","it":[{"ind":0,"ty":"sh","ix":1,"ks":{"a":0,"k":{"i":[[0,0],[0,0]],"o":[[0,0],[0,0]],"v":[[270.762,138.681],[-270.762,-138.682]],"c":false},"ix":2},"nm":"Path 1","mn":"ADBE Vector Shape - Group","hd":false},{"ty":"st","c":{"a":0,"k":[0.361000001197,0.361000001197,0.426999978458,1],"ix":3},"o":{"a":0,"k":100,"ix":4},"w":{"a":0,"k":2,"ix":5},"lc":1,"lj":1,"ml":10,"bm":0,"nm":"Stroke 1","mn":"ADBE Vector Graphic - Stroke","hd":false},{"ty":"tr","p":{"a":0,"k":[271.762,139.682],"ix":2},"a":{"a":0,"k":[0,0],"ix":1},"s":{"a":0,"k":[100,100],"ix":3},"r":{"a":0,"k":0,"ix":6},"o":{"a":0,"k":100,"ix":7},"sk":{"a":0,"k":0,"ix":4},"sa":{"a":0,"k":0,"ix":5},"nm":"Transform"}],"nm":"Group 1","np":2,"cix":2,"bm":0,"ix":1,"mn":"ADBE Vector Group","hd":false}],"ip":0,"op":1200,"st":0,"bm":0},{"ddd":0,"ind":4,"ty":4,"nm":"Layer 4 Outlines","sr":1,"ks":{"o":{"a":0,"k":100,"ix":11},"r":{"a":0,"k":0,"ix":10},"p":{"a":0,"k":[565.603,343.576,0],"ix":2},"a":{"a":0,"k":[270.18,139.52,0],"ix":1},"s":{"a":0,"k":[100,100,100],"ix":6}},"ao":0,"shapes":[{"ty":"gr","it":[{"ind":0,"ty":"sh","ix":1,"ks":{"a":0,"k":{"i":[[0,0],[0,0]],"o":[[0,0],[0,0]],"v":[[269.18,138.52],[-269.18,-138.52]],"c":false},"ix":2},"nm":"Path 1","mn":"ADBE Vector Shape - Group","hd":false},{"ty":"st","c":{"a":0,"k":[0.361000001197,0.361000001197,0.426999978458,1],"ix":3},"o":{"a":0,"k":100,"ix":4},"w":{"a":0,"k":2,"ix":5},"lc":1,"lj":1,"ml":10,"bm":0,"nm":"Stroke 1","mn":"ADBE Vector Graphic - Stroke","hd":false},{"ty":"tr","p":{"a":0,"k":[270.18,139.52],"ix":2},"a":{"a":0,"k":[0,0],"ix":1},"s":{"a":0,"k":[100,100],"ix":3},"r":{"a":0,"k":0,"ix":6},"o":{"a":0,"k":100,"ix":7},"sk":{"a":0,"k":0,"ix":4},"sa":{"a":0,"k":0,"ix":5},"nm":"Transform"}],"nm":"Group 1","np":2,"cix":2,"bm":0,"ix":1,"mn":"ADBE Vector Group","hd":false}],"ip":0,"op":1200,"st":0,"bm":0},{"ddd":0,"ind":5,"ty":4,"nm":"Layer 5 Outlines","sr":1,"ks":{"o":{"a":0,"k":100,"ix":11},"r":{"a":0,"k":0,"ix":10},"p":{"a":0,"k":[527.865,334.943,0],"ix":2},"a":{"a":0,"k":[286.591,151.339,0],"ix":1},"s":{"a":0,"k":[100,100,100],"ix":6}},"ao":0,"shapes":[{"ty":"gr","it":[{"ind":0,"ty":"sh","ix":1,"ks":{"a":0,"k":{"i":[[0,0],[0,0]],"o":[[0,0],[0,0]],"v":[[285.091,149.839],[-285.091,-149.839]],"c":false},"ix":2},"nm":"Path 1","mn":"ADBE Vector Shape - Group","hd":false},{"ty":"st","c":{"a":0,"k":[0.361000001197,0.361000001197,0.426999978458,1],"ix":3},"o":{"a":0,"k":100,"ix":4},"w":{"a":0,"k":3,"ix":5},"lc":1,"lj":1,"ml":10,"bm":0,"nm":"Stroke 1","mn":"ADBE Vector Graphic - Stroke","hd":false},{"ty":"tr","p":{"a":0,"k":[286.591,151.34],"ix":2},"a":{"a":0,"k":[0,0],"ix":1},"s":{"a":0,"k":[100,100],"ix":3},"r":{"a":0,"k":0,"ix":6},"o":{"a":0,"k":100,"ix":7},"sk":{"a":0,"k":0,"ix":4},"sa":{"a":0,"k":0,"ix":5},"nm":"Transform"}],"nm":"Group 1","np":2,"cix":2,"bm":0,"ix":1,"mn":"ADBE Vector Group","hd":false}],"ip":0,"op":1200,"st":0,"bm":0},{"ddd":0,"ind":6,"ty":4,"nm":"Layer 6 Outlines","sr":1,"ks":{"o":{"a":0,"k":100,"ix":11},"r":{"a":0,"k":0,"ix":10},"p":{"a":0,"k":[515.997,342.171,0],"ix":2},"a":{"a":0,"k":[276.223,148.792,0],"ix":1},"s":{"a":0,"k":[100,100,100],"ix":6}},"ao":0,"shapes":[{"ty":"gr","it":[{"ind":0,"ty":"sh","ix":1,"ks":{"a":0,"k":{"i":[[0,0],[0,0]],"o":[[0,0],[0,0]],"v":[[274.223,146.791],[-274.223,-146.792]],"c":false},"ix":2},"nm":"Path 1","mn":"ADBE Vector Shape - Group","hd":false},{"ty":"st","c":{"a":0,"k":[0.361000001197,0.361000001197,0.426999978458,1],"ix":3},"o":{"a":0,"k":100,"ix":4},"w":{"a":0,"k":4,"ix":5},"lc":1,"lj":1,"ml":10,"bm":0,"nm":"Stroke 1","mn":"ADBE Vector Graphic - Stroke","hd":false},{"ty":"tr","p":{"a":0,"k":[276.223,148.792],"ix":2},"a":{"a":0,"k":[0,0],"ix":1},"s":{"a":0,"k":[100,100],"ix":3},"r":{"a":0,"k":0,"ix":6},"o":{"a":0,"k":100,"ix":7},"sk":{"a":0,"k":0,"ix":4},"sa":{"a":0,"k":0,"ix":5},"nm":"Transform"}],"nm":"Group 1","np":2,"cix":2,"bm":0,"ix":1,"mn":"ADBE Vector Group","hd":false}],"ip":0,"op":1200,"st":0,"bm":0},{"ddd":0,"ind":7,"ty":4,"nm":"Layer 7 Outlines","sr":1,"ks":{"o":{"a":0,"k":100,"ix":11},"r":{"a":0,"k":0,"ix":10},"p":{"a":0,"k":[470.517,345.414,0],"ix":2},"a":{"a":0,"k":[277.711,152.534,0],"ix":1},"s":{"a":0,"k":[100,100,100],"ix":6}},"ao":0,"shapes":[{"ty":"gr","it":[{"ind":0,"ty":"sh","ix":1,"ks":{"a":0,"k":{"i":[[0,0],[0,0]],"o":[[0,0],[0,0]],"v":[[275.211,150.034],[-275.211,-150.034]],"c":false},"ix":2},"nm":"Path 1","mn":"ADBE Vector Shape - Group","hd":false},{"ty":"st","c":{"a":0,"k":[0.361000001197,0.361000001197,0.426999978458,1],"ix":3},"o":{"a":0,"k":100,"ix":4},"w":{"a":0,"k":5,"ix":5},"lc":1,"lj":1,"ml":10,"bm":0,"nm":"Stroke 1","mn":"ADBE Vector Graphic - Stroke","hd":false},{"ty":"tr","p":{"a":0,"k":[277.711,152.534],"ix":2},"a":{"a":0,"k":[0,0],"ix":1},"s":{"a":0,"k":[100,100],"ix":3},"r":{"a":0,"k":0,"ix":6},"o":{"a":0,"k":100,"ix":7},"sk":{"a":0,"k":0,"ix":4},"sa":{"a":0,"k":0,"ix":5},"nm":"Transform"}],"nm":"Group 1","np":2,"cix":2,"bm":0,"ix":1,"mn":"ADBE Vector Group","hd":false}],"ip":0,"op":1200,"st":0,"bm":0},{"ddd":0,"ind":8,"ty":4,"nm":"Layer 8 Outlines","sr":1,"ks":{"o":{"a":0,"k":100,"ix":11},"r":{"a":0,"k":0,"ix":10},"p":{"a":0,"k":[1335.938,729.855,0],"ix":2},"a":{"a":0,"k":[252.51,133.085,0],"ix":1},"s":{"a":0,"k":[100,100,100],"ix":6}},"ao":0,"shapes":[{"ty":"gr","it":[{"ind":0,"ty":"sh","ix":1,"ks":{"a":0,"k":{"i":[[0,0],[0,0]],"o":[[0,0],[0,0]],"v":[[-251.509,-132.085],[251.509,132.085]],"c":false},"ix":2},"nm":"Path 1","mn":"ADBE Vector Shape - Group","hd":false},{"ty":"st","c":{"a":0,"k":[0.361000001197,0.361000001197,0.426999978458,1],"ix":3},"o":{"a":0,"k":100,"ix":4},"w":{"a":0,"k":2,"ix":5},"lc":1,"lj":1,"ml":10,"bm":0,"nm":"Stroke 1","mn":"ADBE Vector Graphic - Stroke","hd":false},{"ty":"tr","p":{"a":0,"k":[252.509,133.085],"ix":2},"a":{"a":0,"k":[0,0],"ix":1},"s":{"a":0,"k":[100,100],"ix":3},"r":{"a":0,"k":0,"ix":6},"o":{"a":0,"k":100,"ix":7},"sk":{"a":0,"k":0,"ix":4},"sa":{"a":0,"k":0,"ix":5},"nm":"Transform"}],"nm":"Group 1","np":2,"cix":2,"bm":0,"ix":1,"mn":"ADBE Vector Group","hd":false}],"ip":0,"op":1200,"st":0,"bm":0},{"ddd":0,"ind":9,"ty":4,"nm":"Layer 9 Outlines","sr":1,"ks":{"o":{"a":0,"k":100,"ix":11},"r":{"a":0,"k":0,"ix":10},"p":{"a":0,"k":[1324.223,739.442,0],"ix":2},"a":{"a":0,"k":[258.46,136.355,0],"ix":1},"s":{"a":0,"k":[100,100,100],"ix":6}},"ao":0,"shapes":[{"ty":"gr","it":[{"ind":0,"ty":"sh","ix":1,"ks":{"a":0,"k":{"i":[[0,0],[0,0]],"o":[[0,0],[0,0]],"v":[[-257.46,-135.355],[257.459,135.356]],"c":false},"ix":2},"nm":"Path 1","mn":"ADBE Vector Shape - Group","hd":false},{"ty":"st","c":{"a":0,"k":[0.361000001197,0.361000001197,0.426999978458,1],"ix":3},"o":{"a":0,"k":100,"ix":4},"w":{"a":0,"k":2,"ix":5},"lc":1,"lj":1,"ml":10,"bm":0,"nm":"Stroke 1","mn":"ADBE Vector Graphic - Stroke","hd":false},{"ty":"tr","p":{"a":0,"k":[258.459,136.355],"ix":2},"a":{"a":0,"k":[0,0],"ix":1},"s":{"a":0,"k":[100,100],"ix":3},"r":{"a":0,"k":0,"ix":6},"o":{"a":0,"k":100,"ix":7},"sk":{"a":0,"k":0,"ix":4},"sa":{"a":0,"k":0,"ix":5},"nm":"Transform"}],"nm":"Group 1","np":2,"cix":2,"bm":0,"ix":1,"mn":"ADBE Vector Group","hd":false}],"ip":0,"op":1200,"st":0,"bm":0},{"ddd":0,"ind":10,"ty":4,"nm":"Layer 10 Outlines","sr":1,"ks":{"o":{"a":0,"k":100,"ix":11},"r":{"a":0,"k":0,"ix":10},"p":{"a":0,"k":[1318.874,753.556,0],"ix":2},"a":{"a":0,"k":[272.29,144.911,0],"ix":1},"s":{"a":0,"k":[100,100,100],"ix":6}},"ao":0,"shapes":[{"ty":"gr","it":[{"ind":0,"ty":"sh","ix":1,"ks":{"a":0,"k":{"i":[[0,0],[0,0]],"o":[[0,0],[0,0]],"v":[[-270.79,-143.411],[270.79,143.411]],"c":false},"ix":2},"nm":"Path 1","mn":"ADBE Vector Shape - Group","hd":false},{"ty":"st","c":{"a":0,"k":[0.361000001197,0.361000001197,0.426999978458,1],"ix":3},"o":{"a":0,"k":100,"ix":4},"w":{"a":0,"k":3,"ix":5},"lc":1,"lj":1,"ml":10,"bm":0,"nm":"Stroke 1","mn":"ADBE Vector Graphic - Stroke","hd":false},{"ty":"tr","p":{"a":0,"k":[272.29,144.911],"ix":2},"a":{"a":0,"k":[0,0],"ix":1},"s":{"a":0,"k":[100,100],"ix":3},"r":{"a":0,"k":0,"ix":6},"o":{"a":0,"k":100,"ix":7},"sk":{"a":0,"k":0,"ix":4},"sa":{"a":0,"k":0,"ix":5},"nm":"Transform"}],"nm":"Group 1","np":2,"cix":2,"bm":0,"ix":1,"mn":"ADBE Vector Group","hd":false}],"ip":0,"op":1200,"st":0,"bm":0},{"ddd":0,"ind":11,"ty":4,"nm":"Layer 11 Outlines","sr":1,"ks":{"o":{"a":0,"k":100,"ix":11},"r":{"a":0,"k":0,"ix":10},"p":{"a":0,"k":[1310.682,767.909,0],"ix":2},"a":{"a":0,"k":[282.756,151.898,0],"ix":1},"s":{"a":0,"k":[100,100,100],"ix":6}},"ao":0,"shapes":[{"ty":"gr","it":[{"ind":0,"ty":"sh","ix":1,"ks":{"a":0,"k":{"i":[[0,0],[0,0]],"o":[[0,0],[0,0]],"v":[[-280.756,-149.898],[280.756,149.897]],"c":false},"ix":2},"nm":"Path 1","mn":"ADBE Vector Shape - Group","hd":false},{"ty":"st","c":{"a":0,"k":[0.361000001197,0.361000001197,0.426999978458,1],"ix":3},"o":{"a":0,"k":100,"ix":4},"w":{"a":0,"k":4,"ix":5},"lc":1,"lj":1,"ml":10,"bm":0,"nm":"Stroke 1","mn":"ADBE Vector Graphic - Stroke","hd":false},{"ty":"tr","p":{"a":0,"k":[282.756,151.897],"ix":2},"a":{"a":0,"k":[0,0],"ix":1},"s":{"a":0,"k":[100,100],"ix":3},"r":{"a":0,"k":0,"ix":6},"o":{"a":0,"k":100,"ix":7},"sk":{"a":0,"k":0,"ix":4},"sa":{"a":0,"k":0,"ix":5},"nm":"Transform"}],"nm":"Group 1","np":2,"cix":2,"bm":0,"ix":1,"mn":"ADBE Vector Group","hd":false}],"ip":0,"op":1200,"st":0,"bm":0},{"ddd":0,"ind":12,"ty":4,"nm":"Layer 12 Outlines","sr":1,"ks":{"o":{"a":0,"k":100,"ix":11},"r":{"a":0,"k":0,"ix":10},"p":{"a":0,"k":[1299.297,779.678,0],"ix":2},"a":{"a":0,"k":[294.14,160.081,0],"ix":1},"s":{"a":0,"k":[100,100,100],"ix":6}},"ao":0,"shapes":[{"ty":"gr","it":[{"ind":0,"ty":"sh","ix":1,"ks":{"a":0,"k":{"i":[[0,0],[0,0]],"o":[[0,0],[0,0]],"v":[[-292.14,-158.081],[292.14,158.08]],"c":false},"ix":2},"nm":"Path 1","mn":"ADBE Vector Shape - Group","hd":false},{"ty":"st","c":{"a":0,"k":[0.361000001197,0.361000001197,0.426999978458,1],"ix":3},"o":{"a":0,"k":100,"ix":4},"w":{"a":0,"k":4,"ix":5},"lc":1,"lj":1,"ml":10,"bm":0,"nm":"Stroke 1","mn":"ADBE Vector Graphic - Stroke","hd":false},{"ty":"tr","p":{"a":0,"k":[294.14,160.081],"ix":2},"a":{"a":0,"k":[0,0],"ix":1},"s":{"a":0,"k":[100,100],"ix":3},"r":{"a":0,"k":0,"ix":6},"o":{"a":0,"k":100,"ix":7},"sk":{"a":0,"k":0,"ix":4},"sa":{"a":0,"k":0,"ix":5},"nm":"Transform"}],"nm":"Group 1","np":2,"cix":2,"bm":0,"ix":1,"mn":"ADBE Vector Group","hd":false}],"ip":0,"op":1200,"st":0,"bm":0},{"ddd":0,"ind":13,"ty":4,"nm":"Layer 13 Outlines","sr":1,"ks":{"o":{"a":0,"k":100,"ix":11},"r":{"a":0,"k":0,"ix":10},"p":{"a":0,"k":[1285.919,792.74,0],"ix":2},"a":{"a":0,"k":[304.029,167.915,0],"ix":1},"s":{"a":0,"k":[100,100,100],"ix":6}},"ao":0,"shapes":[{"ty":"gr","it":[{"ind":0,"ty":"sh","ix":1,"ks":{"a":0,"k":{"i":[[0,0],[0,0]],"o":[[0,0],[0,0]],"v":[[-301.529,-165.416],[301.529,165.415]],"c":false},"ix":2},"nm":"Path 1","mn":"ADBE Vector Shape - Group","hd":false},{"ty":"st","c":{"a":0,"k":[0.361000001197,0.361000001197,0.426999978458,1],"ix":3},"o":{"a":0,"k":100,"ix":4},"w":{"a":0,"k":5,"ix":5},"lc":1,"lj":1,"ml":10,"bm":0,"nm":"Stroke 1","mn":"ADBE Vector Graphic - Stroke","hd":false},{"ty":"tr","p":{"a":0,"k":[304.029,167.915],"ix":2},"a":{"a":0,"k":[0,0],"ix":1},"s":{"a":0,"k":[100,100],"ix":3},"r":{"a":0,"k":0,"ix":6},"o":{"a":0,"k":100,"ix":7},"sk":{"a":0,"k":0,"ix":4},"sa":{"a":0,"k":0,"ix":5},"nm":"Transform"}],"nm":"Group 1","np":2,"cix":2,"bm":0,"ix":1,"mn":"ADBE Vector Group","hd":false}],"ip":0,"op":1200,"st":0,"bm":0},{"ddd":0,"ind":14,"ty":4,"nm":"Layer 14 Outlines","sr":1,"ks":{"o":{"a":1,"k":[{"i":{"x":[0.667],"y":[1]},"o":{"x":[0.333],"y":[0]},"t":31,"s":[30]},{"i":{"x":[0.667],"y":[1]},"o":{"x":[0.333],"y":[0]},"t":60,"s":[100]},{"i":{"x":[0.667],"y":[1]},"o":{"x":[0.333],"y":[0]},"t":180,"s":[100]},{"i":{"x":[0.833],"y":[1]},"o":{"x":[0.167],"y":[0]},"t":210,"s":[30]},{"i":{"x":[0.667],"y":[1]},"o":{"x":[0.333],"y":[0]},"t":265,"s":[30]},{"i":{"x":[0.667],"y":[1]},"o":{"x":[0.333],"y":[0]},"t":294,"s":[100]},{"i":{"x":[0.667],"y":[1]},"o":{"x":[0.333],"y":[0]},"t":414,"s":[100]},{"t":444,"s":[30]}],"ix":11},"r":{"a":0,"k":0,"ix":10},"p":{"a":1,"k":[{"i":{"x":0.833,"y":0.833},"o":{"x":0.167,"y":0.167},"t":31,"s":[907.841,668.893,0],"to":[0.583,-0.333,0],"ti":[-0.583,0.333,0]},{"i":{"x":0.833,"y":0.833},"o":{"x":0.167,"y":0.167},"t":60,"s":[911.341,666.893,0],"to":[0,0,0],"ti":[0,0,0]},{"i":{"x":0.833,"y":0.833},"o":{"x":0.167,"y":0.167},"t":180,"s":[911.341,666.893,0],"to":[-0.583,0.333,0],"ti":[0.583,-0.333,0]},{"i":{"x":0.833,"y":0.833},"o":{"x":0.167,"y":0.167},"t":210,"s":[907.841,668.893,0],"to":[0,0,0],"ti":[0,0,0]},{"i":{"x":0.833,"y":0.833},"o":{"x":0.167,"y":0.167},"t":265,"s":[907.841,668.893,0],"to":[0.583,-0.333,0],"ti":[-0.583,0.333,0]},{"i":{"x":0.833,"y":0.833},"o":{"x":0.167,"y":0.167},"t":294,"s":[911.341,666.893,0],"to":[0,0,0],"ti":[0,0,0]},{"i":{"x":0.833,"y":0.833},"o":{"x":0.167,"y":0.167},"t":414,"s":[911.341,666.893,0],"to":[-0.583,0.333,0],"ti":[0.583,-0.333,0]},{"t":444,"s":[907.841,668.893,0]}],"ix":2},"a":{"a":0,"k":[14.577,19.162,0],"ix":1},"s":{"a":0,"k":[100,100,100],"ix":6}},"ao":0,"shapes":[{"ty":"gr","it":[{"ind":0,"ty":"sh","ix":1,"ks":{"a":0,"k":{"i":[[-4.664,-8.9],[5.337,-2.796],[4.663,8.9],[-5.337,2.797]],"o":[[4.664,8.9],[-5.337,2.797],[-4.664,-8.9],[5.336,-2.796]],"v":[[9.663,-5.064],[8.444,16.116],[-9.663,5.062],[-8.444,-16.116]],"c":true},"ix":2},"nm":"Path 1","mn":"ADBE Vector Shape - Group","hd":false},{"ty":"fl","c":{"a":1,"k":[{"i":{"x":[0.833],"y":[0.833]},"o":{"x":[0.167],"y":[0.167]},"t":210,"s":[1,0,1,1]},{"t":265,"s":[0,0.337254911661,1,1]}],"ix":4},"o":{"a":0,"k":100,"ix":5},"r":1,"bm":0,"nm":"Fill 1","mn":"ADBE Vector Graphic - Fill","hd":false},{"ty":"tr","p":{"a":0,"k":[14.577,19.163],"ix":2},"a":{"a":0,"k":[0,0],"ix":1},"s":{"a":0,"k":[100,100],"ix":3},"r":{"a":0,"k":0,"ix":6},"o":{"a":0,"k":100,"ix":7},"sk":{"a":0,"k":0,"ix":4},"sa":{"a":0,"k":0,"ix":5},"nm":"Transform"}],"nm":"Group 1","np":2,"cix":2,"bm":0,"ix":1,"mn":"ADBE Vector Group","hd":false}],"ip":0,"op":1200,"st":0,"bm":0},{"ddd":0,"ind":15,"ty":4,"nm":"Layer 15 Outlines","sr":1,"ks":{"o":{"a":0,"k":100,"ix":11},"r":{"a":0,"k":0,"ix":10},"p":{"a":0,"k":[909.919,667.507,0],"ix":2},"a":{"a":0,"k":[17.169,20.7,0],"ix":1},"s":{"a":0,"k":[100,100,100],"ix":6}},"ao":0,"shapes":[{"ty":"gr","it":[{"ind":0,"ty":"sh","ix":1,"ks":{"a":0,"k":{"i":[[4.664,8.9],[5.336,-2.796],[0,0],[0.373,-0.195],[0.437,-0.404],[0,0],[0,0],[-4.177,-7.974],[-5.279,1.436],[0,0],[0,0],[-0.408,0.213],[-0.279,0.207],[0,0]],"o":[[-4.664,-8.9],[0,0],[-0.399,0.121],[-0.533,0.279],[0,0],[0,0],[-3.884,3.681],[4.285,8.178],[0,0],[0,0],[0.438,-0.125],[0.311,-0.164],[0,0],[5.337,-2.796]],"v":[[11.255,-5.601],[-6.852,-16.653],[-9.361,-15.195],[-10.522,-14.73],[-11.962,-13.684],[-12.028,-13.646],[-12.02,-13.631],[-11.742,6.449],[5.008,18.014],[5.017,18.031],[5.091,17.994],[6.366,17.502],[7.248,16.941],[10.036,15.579]],"c":true},"ix":2},"nm":"Path 1","mn":"ADBE Vector Shape - Group","hd":false},{"ty":"st","c":{"a":0,"k":[0.360784313725,0.360784313725,0.427451010311,1],"ix":3},"o":{"a":0,"k":44,"ix":4},"w":{"a":0,"k":0.5,"ix":5},"lc":1,"lj":1,"ml":10,"bm":0,"nm":"Stroke 1","mn":"ADBE Vector Graphic - Stroke","hd":false},{"ty":"tr","p":{"a":0,"k":[17.169,20.7],"ix":2},"a":{"a":0,"k":[0,0],"ix":1},"s":{"a":0,"k":[100,100],"ix":3},"r":{"a":0,"k":0,"ix":6},"o":{"a":0,"k":100,"ix":7},"sk":{"a":0,"k":0,"ix":4},"sa":{"a":0,"k":0,"ix":5},"nm":"Transform"}],"nm":"Group 1","np":2,"cix":2,"bm":0,"ix":1,"mn":"ADBE Vector Group","hd":false},{"ty":"fl","c":{"a":0,"k":[0.360784313725,0.360784313725,0.427451010311,1],"ix":4},"o":{"a":0,"k":26,"ix":5},"r":1,"bm":0,"nm":"Fill 1","mn":"ADBE Vector Graphic - Fill","hd":false}],"ip":0,"op":1200,"st":0,"bm":0},{"ddd":0,"ind":16,"ty":4,"nm":"Layer 16 Outlines","sr":1,"ks":{"o":{"a":0,"k":100,"ix":11},"r":{"a":0,"k":0,"ix":10},"p":{"a":0,"k":[1042.804,568.795,0],"ix":2},"a":{"a":0,"k":[45.813,22.356,0],"ix":1},"s":{"a":0,"k":[100,100,100],"ix":6}},"ao":0,"shapes":[{"ty":"gr","it":[{"ind":0,"ty":"sh","ix":1,"ks":{"a":0,"k":{"i":[[0,0],[0,0],[2.287,-4.323],[0,0]],"o":[[0,0],[0,0],[-2.286,4.323],[0,0]],"v":[[44.564,21.106],[-34.587,-20.441],[-42.277,-16.783],[-43.053,-9.993]],"c":false},"ix":2},"nm":"Path 1","mn":"ADBE Vector Shape - Group","hd":false},{"ty":"st","c":{"a":0,"k":[0.361000001197,0.361000001197,0.426999978458,1],"ix":3},"o":{"a":0,"k":100,"ix":4},"w":{"a":0,"k":0.5,"ix":5},"lc":1,"lj":1,"ml":10,"bm":0,"nm":"Stroke 1","mn":"ADBE Vector Graphic - Stroke","hd":false},{"ty":"tr","p":{"a":0,"k":[45.813,22.357],"ix":2},"a":{"a":0,"k":[0,0],"ix":1},"s":{"a":0,"k":[100,100],"ix":3},"r":{"a":0,"k":0,"ix":6},"o":{"a":0,"k":100,"ix":7},"sk":{"a":0,"k":0,"ix":4},"sa":{"a":0,"k":0,"ix":5},"nm":"Transform"}],"nm":"Group 1","np":2,"cix":2,"bm":0,"ix":1,"mn":"ADBE Vector Group","hd":false}],"ip":0,"op":1200,"st":0,"bm":0},{"ddd":0,"ind":17,"ty":4,"nm":"Layer 17 Outlines","sr":1,"ks":{"o":{"a":0,"k":100,"ix":11},"r":{"a":0,"k":0,"ix":10},"p":{"a":0,"k":[1076.699,602.832,0],"ix":2},"a":{"a":0,"k":[3.621,2.232,0],"ix":1},"s":{"a":0,"k":[100,100,100],"ix":6}},"ao":0,"shapes":[{"ty":"gr","it":[{"ind":0,"ty":"sh","ix":1,"ks":{"a":0,"k":{"i":[[0,0],[0,0]],"o":[[0,0],[0,0]],"v":[[3.371,1.982],[-3.371,-1.982]],"c":false},"ix":2},"nm":"Path 1","mn":"ADBE Vector Shape - Group","hd":false},{"ty":"st","c":{"a":0,"k":[0.361000001197,0.361000001197,0.426999978458,1],"ix":3},"o":{"a":0,"k":100,"ix":4},"w":{"a":0,"k":0.5,"ix":5},"lc":1,"lj":1,"ml":10,"bm":0,"nm":"Stroke 1","mn":"ADBE Vector Graphic - Stroke","hd":false},{"ty":"tr","p":{"a":0,"k":[3.621,2.233],"ix":2},"a":{"a":0,"k":[0,0],"ix":1},"s":{"a":0,"k":[100,100],"ix":3},"r":{"a":0,"k":0,"ix":6},"o":{"a":0,"k":100,"ix":7},"sk":{"a":0,"k":0,"ix":4},"sa":{"a":0,"k":0,"ix":5},"nm":"Transform"}],"nm":"Group 1","np":2,"cix":2,"bm":0,"ix":1,"mn":"ADBE Vector Group","hd":false}],"ip":0,"op":1200,"st":0,"bm":0},{"ddd":0,"ind":18,"ty":4,"nm":"Layer 18 Outlines","sr":1,"ks":{"o":{"a":0,"k":100,"ix":11},"r":{"a":0,"k":0,"ix":10},"p":{"a":0,"k":[1058.336,608.872,0],"ix":2},"a":{"a":0,"k":[3.928,2.164,0],"ix":1},"s":{"a":0,"k":[100,100,100],"ix":6}},"ao":0,"shapes":[{"ty":"gr","it":[{"ind":0,"ty":"sh","ix":1,"ks":{"a":0,"k":{"i":[[0,0],[0,0]],"o":[[0,0],[0,0]],"v":[[3.678,1.914],[-3.678,-1.914]],"c":false},"ix":2},"nm":"Path 1","mn":"ADBE Vector Shape - Group","hd":false},{"ty":"st","c":{"a":0,"k":[0.361000001197,0.361000001197,0.426999978458,1],"ix":3},"o":{"a":0,"k":100,"ix":4},"w":{"a":0,"k":0.5,"ix":5},"lc":1,"lj":1,"ml":10,"bm":0,"nm":"Stroke 1","mn":"ADBE Vector Graphic - Stroke","hd":false},{"ty":"tr","p":{"a":0,"k":[3.928,2.164],"ix":2},"a":{"a":0,"k":[0,0],"ix":1},"s":{"a":0,"k":[100,100],"ix":3},"r":{"a":0,"k":0,"ix":6},"o":{"a":0,"k":100,"ix":7},"sk":{"a":0,"k":0,"ix":4},"sa":{"a":0,"k":0,"ix":5},"nm":"Transform"}],"nm":"Group 1","np":2,"cix":2,"bm":0,"ix":1,"mn":"ADBE Vector Group","hd":false}],"ip":0,"op":1200,"st":0,"bm":0},{"ddd":0,"ind":19,"ty":4,"nm":"Layer 19 Outlines","sr":1,"ks":{"o":{"a":0,"k":100,"ix":11},"r":{"a":0,"k":0,"ix":10},"p":{"a":0,"k":[1024.577,573.7,0],"ix":2},"a":{"a":0,"k":[46.376,23.77,0],"ix":1},"s":{"a":0,"k":[100,100,100],"ix":6}},"ao":0,"shapes":[{"ty":"gr","it":[{"ind":0,"ty":"sh","ix":1,"ks":{"a":0,"k":{"i":[[0,0],[0,0],[3.326,-4.323],[0,0]],"o":[[0,0],[0,0],[-3.325,4.323],[0,0]],"v":[[45.126,22.52],[-30.993,-18.197],[-41.801,-18.197],[-44.618,-9.255]],"c":false},"ix":2},"nm":"Path 1","mn":"ADBE Vector Shape - Group","hd":false},{"ty":"st","c":{"a":0,"k":[0.361000001197,0.361000001197,0.426999978458,1],"ix":3},"o":{"a":0,"k":100,"ix":4},"w":{"a":0,"k":0.5,"ix":5},"lc":1,"lj":1,"ml":10,"bm":0,"nm":"Stroke 1","mn":"ADBE Vector Graphic - Stroke","hd":false},{"ty":"tr","p":{"a":0,"k":[46.376,23.77],"ix":2},"a":{"a":0,"k":[0,0],"ix":1},"s":{"a":0,"k":[100,100],"ix":3},"r":{"a":0,"k":0,"ix":6},"o":{"a":0,"k":100,"ix":7},"sk":{"a":0,"k":0,"ix":4},"sa":{"a":0,"k":0,"ix":5},"nm":"Transform"}],"nm":"Group 1","np":2,"cix":2,"bm":0,"ix":1,"mn":"ADBE Vector Group","hd":false}],"ip":0,"op":1200,"st":0,"bm":0},{"ddd":0,"ind":20,"ty":4,"nm":"Layer 20 Outlines","sr":1,"ks":{"o":{"a":0,"k":100,"ix":11},"r":{"a":0,"k":0,"ix":10},"p":{"a":0,"k":[1040.894,615.871,0],"ix":2},"a":{"a":0,"k":[4.501,2.391,0],"ix":1},"s":{"a":0,"k":[100,100,100],"ix":6}},"ao":0,"shapes":[{"ty":"gr","it":[{"ind":0,"ty":"sh","ix":1,"ks":{"a":0,"k":{"i":[[0,0],[0,0]],"o":[[0,0],[0,0]],"v":[[4.252,2.141],[-4.252,-2.141]],"c":false},"ix":2},"nm":"Path 1","mn":"ADBE Vector Shape - Group","hd":false},{"ty":"st","c":{"a":0,"k":[0.361000001197,0.361000001197,0.426999978458,1],"ix":3},"o":{"a":0,"k":100,"ix":4},"w":{"a":0,"k":0.5,"ix":5},"lc":1,"lj":1,"ml":10,"bm":0,"nm":"Stroke 1","mn":"ADBE Vector Graphic - Stroke","hd":false},{"ty":"tr","p":{"a":0,"k":[4.501,2.391],"ix":2},"a":{"a":0,"k":[0,0],"ix":1},"s":{"a":0,"k":[100,100],"ix":3},"r":{"a":0,"k":0,"ix":6},"o":{"a":0,"k":100,"ix":7},"sk":{"a":0,"k":0,"ix":4},"sa":{"a":0,"k":0,"ix":5},"nm":"Transform"}],"nm":"Group 1","np":2,"cix":2,"bm":0,"ix":1,"mn":"ADBE Vector Group","hd":false}],"ip":0,"op":1200,"st":0,"bm":0},{"ddd":0,"ind":21,"ty":4,"nm":"Layer 21 Outlines","sr":1,"ks":{"o":{"a":0,"k":100,"ix":11},"r":{"a":0,"k":0,"ix":10},"p":{"a":0,"k":[1005.094,580.054,0],"ix":2},"a":{"a":0,"k":[47.178,23.472,0],"ix":1},"s":{"a":0,"k":[100,100,100],"ix":6}},"ao":0,"shapes":[{"ty":"gr","it":[{"ind":0,"ty":"sh","ix":1,"ks":{"a":0,"k":{"i":[[0,0],[0,0],[1.829,-0.665],[-0.166,-7.315]],"o":[[0,0],[0,0],[-1.829,0.665],[0,0]],"v":[[45.928,22.222],[-34.123,-20.394],[-39.61,-21.558],[-45.762,-11.084]],"c":false},"ix":2},"nm":"Path 1","mn":"ADBE Vector Shape - Group","hd":false},{"ty":"st","c":{"a":0,"k":[0.361000001197,0.361000001197,0.426999978458,1],"ix":3},"o":{"a":0,"k":100,"ix":4},"w":{"a":0,"k":0.5,"ix":5},"lc":1,"lj":1,"ml":10,"bm":0,"nm":"Stroke 1","mn":"ADBE Vector Graphic - Stroke","hd":false},{"ty":"tr","p":{"a":0,"k":[47.178,23.473],"ix":2},"a":{"a":0,"k":[0,0],"ix":1},"s":{"a":0,"k":[100,100],"ix":3},"r":{"a":0,"k":0,"ix":6},"o":{"a":0,"k":100,"ix":7},"sk":{"a":0,"k":0,"ix":4},"sa":{"a":0,"k":0,"ix":5},"nm":"Transform"}],"nm":"Group 1","np":2,"cix":2,"bm":0,"ix":1,"mn":"ADBE Vector Group","hd":false}],"ip":0,"op":1200,"st":0,"bm":0},{"ddd":0,"ind":22,"ty":4,"nm":"Layer 22 Outlines","sr":1,"ks":{"o":{"a":0,"k":100,"ix":11},"r":{"a":0,"k":0,"ix":10},"p":{"a":0,"k":[1020.098,620.265,0],"ix":2},"a":{"a":0,"k":[7.14,3.723,0],"ix":1},"s":{"a":0,"k":[100,100,100],"ix":6}},"ao":0,"shapes":[{"ty":"gr","it":[{"ind":0,"ty":"sh","ix":1,"ks":{"a":0,"k":{"i":[[0,0],[0,0]],"o":[[0,0],[0,0]],"v":[[6.89,3.473],[-6.89,-3.473]],"c":false},"ix":2},"nm":"Path 1","mn":"ADBE Vector Shape - Group","hd":false},{"ty":"st","c":{"a":0,"k":[0.361000001197,0.361000001197,0.426999978458,1],"ix":3},"o":{"a":0,"k":100,"ix":4},"w":{"a":0,"k":0.5,"ix":5},"lc":1,"lj":1,"ml":10,"bm":0,"nm":"Stroke 1","mn":"ADBE Vector Graphic - Stroke","hd":false},{"ty":"tr","p":{"a":0,"k":[7.139,3.723],"ix":2},"a":{"a":0,"k":[0,0],"ix":1},"s":{"a":0,"k":[100,100],"ix":3},"r":{"a":0,"k":0,"ix":6},"o":{"a":0,"k":100,"ix":7},"sk":{"a":0,"k":0,"ix":4},"sa":{"a":0,"k":0,"ix":5},"nm":"Transform"}],"nm":"Group 1","np":2,"cix":2,"bm":0,"ix":1,"mn":"ADBE Vector Group","hd":false}],"ip":0,"op":1200,"st":0,"bm":0},{"ddd":0,"ind":23,"ty":4,"nm":"Layer 23 Outlines","sr":1,"ks":{"o":{"a":0,"k":100,"ix":11},"r":{"a":0,"k":0,"ix":10},"p":{"a":0,"k":[983.509,585.509,0],"ix":2},"a":{"a":0,"k":[48.43,23.442,0],"ix":1},"s":{"a":0,"k":[100,100,100],"ix":6}},"ao":0,"shapes":[{"ty":"gr","it":[{"ind":0,"ty":"sh","ix":1,"ks":{"a":0,"k":{"i":[[0,0],[0,0],[-2.191,-12.435]],"o":[[0,0],[0,0],[0,0]],"v":[[47.18,22.192],[-35.65,-22.192],[-44.989,-9.685]],"c":false},"ix":2},"nm":"Path 1","mn":"ADBE Vector Shape - Group","hd":false},{"ty":"st","c":{"a":0,"k":[0.361000001197,0.361000001197,0.426999978458,1],"ix":3},"o":{"a":0,"k":100,"ix":4},"w":{"a":0,"k":0.5,"ix":5},"lc":1,"lj":1,"ml":10,"bm":0,"nm":"Stroke 1","mn":"ADBE Vector Graphic - Stroke","hd":false},{"ty":"tr","p":{"a":0,"k":[48.43,23.442],"ix":2},"a":{"a":0,"k":[0,0],"ix":1},"s":{"a":0,"k":[100,100],"ix":3},"r":{"a":0,"k":0,"ix":6},"o":{"a":0,"k":100,"ix":7},"sk":{"a":0,"k":0,"ix":4},"sa":{"a":0,"k":0,"ix":5},"nm":"Transform"}],"nm":"Group 1","np":2,"cix":2,"bm":0,"ix":1,"mn":"ADBE Vector Group","hd":false}],"ip":0,"op":1200,"st":0,"bm":0},{"ddd":0,"ind":24,"ty":4,"nm":"Layer 24 Outlines","sr":1,"ks":{"o":{"a":0,"k":100,"ix":11},"r":{"a":0,"k":0,"ix":10},"p":{"a":0,"k":[963.019,590.768,0],"ix":2},"a":{"a":0,"k":[48.327,24.212,0],"ix":1},"s":{"a":0,"k":[100,100,100],"ix":6}},"ao":0,"shapes":[{"ty":"gr","it":[{"ind":0,"ty":"sh","ix":1,"ks":{"a":0,"k":{"i":[[0,0],[0,0],[1.829,-7.982],[0,0]],"o":[[0,0],[0,0],[-0.493,4.525],[0,0]],"v":[[47.077,22.961],[-37.439,-21.797],[-46.584,-14.979],[-44.567,-7.523]],"c":false},"ix":2},"nm":"Path 1","mn":"ADBE Vector Shape - Group","hd":false},{"ty":"st","c":{"a":0,"k":[0.361000001197,0.361000001197,0.426999978458,1],"ix":3},"o":{"a":0,"k":100,"ix":4},"w":{"a":0,"k":0.5,"ix":5},"lc":1,"lj":1,"ml":10,"bm":0,"nm":"Stroke 1","mn":"ADBE Vector Graphic - Stroke","hd":false},{"ty":"tr","p":{"a":0,"k":[48.327,24.212],"ix":2},"a":{"a":0,"k":[0,0],"ix":1},"s":{"a":0,"k":[100,100],"ix":3},"r":{"a":0,"k":0,"ix":6},"o":{"a":0,"k":100,"ix":7},"sk":{"a":0,"k":0,"ix":4},"sa":{"a":0,"k":0,"ix":5},"nm":"Transform"}],"nm":"Group 1","np":2,"cix":2,"bm":0,"ix":1,"mn":"ADBE Vector Group","hd":false}],"ip":0,"op":1200,"st":0,"bm":0},{"ddd":0,"ind":25,"ty":4,"nm":"Layer 25 Outlines","sr":1,"ks":{"o":{"a":0,"k":100,"ix":11},"r":{"a":0,"k":0,"ix":10},"p":{"a":0,"k":[997.376,626.092,0],"ix":2},"a":{"a":0,"k":[7.092,3.622,0],"ix":1},"s":{"a":0,"k":[100,100,100],"ix":6}},"ao":0,"shapes":[{"ty":"gr","it":[{"ind":0,"ty":"sh","ix":1,"ks":{"a":0,"k":{"i":[[0,0],[0,0]],"o":[[0,0],[0,0]],"v":[[6.843,3.372],[-6.843,-3.372]],"c":false},"ix":2},"nm":"Path 1","mn":"ADBE Vector Shape - Group","hd":false},{"ty":"st","c":{"a":0,"k":[0.361000001197,0.361000001197,0.426999978458,1],"ix":3},"o":{"a":0,"k":100,"ix":4},"w":{"a":0,"k":0.5,"ix":5},"lc":1,"lj":1,"ml":10,"bm":0,"nm":"Stroke 1","mn":"ADBE Vector Graphic - Stroke","hd":false},{"ty":"tr","p":{"a":0,"k":[7.092,3.623],"ix":2},"a":{"a":0,"k":[0,0],"ix":1},"s":{"a":0,"k":[100,100],"ix":3},"r":{"a":0,"k":0,"ix":6},"o":{"a":0,"k":100,"ix":7},"sk":{"a":0,"k":0,"ix":4},"sa":{"a":0,"k":0,"ix":5},"nm":"Transform"}],"nm":"Group 1","np":2,"cix":2,"bm":0,"ix":1,"mn":"ADBE Vector Group","hd":false}],"ip":0,"op":1200,"st":0,"bm":0},{"ddd":0,"ind":26,"ty":4,"nm":"Layer 26 Outlines","sr":1,"ks":{"o":{"a":0,"k":100,"ix":11},"r":{"a":0,"k":0,"ix":10},"p":{"a":0,"k":[938.414,604.492,0],"ix":2},"a":{"a":0,"k":[50.164,31.949,0],"ix":1},"s":{"a":0,"k":[100,100,100],"ix":6}},"ao":0,"shapes":[{"ty":"gr","it":[{"ind":0,"ty":"sh","ix":1,"ks":{"a":0,"k":{"i":[[0,0],[0,0],[3.657,-7.648],[0,0],[0,0]],"o":[[0,0],[0,0],[-2.827,6.651],[0,0],[0,0]],"v":[[48.915,14.964],[-37.454,-30.445],[-46.087,-23.051],[-44.663,-13.403],[43.038,30.699]],"c":false},"ix":2},"nm":"Path 1","mn":"ADBE Vector Shape - Group","hd":false},{"ty":"st","c":{"a":0,"k":[0.361000001197,0.361000001197,0.426999978458,1],"ix":3},"o":{"a":0,"k":100,"ix":4},"w":{"a":0,"k":0.5,"ix":5},"lc":1,"lj":1,"ml":10,"bm":0,"nm":"Stroke 1","mn":"ADBE Vector Graphic - Stroke","hd":false},{"ty":"tr","p":{"a":0,"k":[50.165,31.949],"ix":2},"a":{"a":0,"k":[0,0],"ix":1},"s":{"a":0,"k":[100,100],"ix":3},"r":{"a":0,"k":0,"ix":6},"o":{"a":0,"k":100,"ix":7},"sk":{"a":0,"k":0,"ix":4},"sa":{"a":0,"k":0,"ix":5},"nm":"Transform"}],"nm":"Group 1","np":2,"cix":2,"bm":0,"ix":1,"mn":"ADBE Vector Group","hd":false}],"ip":0,"op":1200,"st":0,"bm":0},{"ddd":0,"ind":27,"ty":4,"nm":"Layer 27 Outlines","sr":1,"ks":{"o":{"a":0,"k":100,"ix":11},"r":{"a":0,"k":0,"ix":10},"p":{"a":0,"k":[1084.429,597.77,0],"ix":2},"a":{"a":0,"k":[8.955,10.372,0],"ix":1},"s":{"a":0,"k":[100,100,100],"ix":6}},"ao":0,"shapes":[{"ty":"gr","it":[{"ind":0,"ty":"sh","ix":1,"ks":{"a":0,"k":{"i":[[1.623,-4.346],[3.36,1.255],[-1.623,4.345],[-3.358,-1.254]],"o":[[-1.623,4.345],[-3.358,-1.254],[1.623,-4.346],[3.36,1.255]],"v":[[6.082,2.271],[-2.939,7.867],[-6.082,-2.272],[2.938,-7.868]],"c":true},"ix":2},"nm":"Path 1","mn":"ADBE Vector Shape - Group","hd":false},{"ty":"st","c":{"a":0,"k":[0.361000001197,0.361000001197,0.426999978458,1],"ix":3},"o":{"a":0,"k":100,"ix":4},"w":{"a":0,"k":0.5,"ix":5},"lc":1,"lj":1,"ml":10,"bm":0,"nm":"Stroke 1","mn":"ADBE Vector Graphic - Stroke","hd":false},{"ty":"tr","p":{"a":0,"k":[8.955,10.372],"ix":2},"a":{"a":0,"k":[0,0],"ix":1},"s":{"a":0,"k":[100,100],"ix":3},"r":{"a":0,"k":0,"ix":6},"o":{"a":0,"k":100,"ix":7},"sk":{"a":0,"k":0,"ix":4},"sa":{"a":0,"k":0,"ix":5},"nm":"Transform"}],"nm":"Group 1","np":2,"cix":2,"bm":0,"ix":1,"mn":"ADBE Vector Group","hd":false}],"ip":0,"op":1200,"st":0,"bm":0},{"ddd":0,"ind":28,"ty":4,"nm":"Layer 28 Outlines","sr":1,"ks":{"o":{"a":0,"k":100,"ix":11},"r":{"a":0,"k":0,"ix":10},"p":{"a":0,"k":[1066.764,604.087,0],"ix":2},"a":{"a":0,"k":[8.955,10.372,0],"ix":1},"s":{"a":0,"k":[100,100,100],"ix":6}},"ao":0,"shapes":[{"ty":"gr","it":[{"ind":0,"ty":"sh","ix":1,"ks":{"a":0,"k":{"i":[[1.623,-4.345],[3.359,1.254],[-1.623,4.346],[-3.358,-1.255]],"o":[[-1.623,4.346],[-3.359,-1.255],[1.623,-4.345],[3.36,1.254]],"v":[[6.082,2.271],[-2.939,7.868],[-6.082,-2.272],[2.938,-7.867]],"c":true},"ix":2},"nm":"Path 1","mn":"ADBE Vector Shape - Group","hd":false},{"ty":"st","c":{"a":0,"k":[0.361000001197,0.361000001197,0.426999978458,1],"ix":3},"o":{"a":0,"k":100,"ix":4},"w":{"a":0,"k":0.5,"ix":5},"lc":1,"lj":1,"ml":10,"bm":0,"nm":"Stroke 1","mn":"ADBE Vector Graphic - Stroke","hd":false},{"ty":"tr","p":{"a":0,"k":[8.955,10.373],"ix":2},"a":{"a":0,"k":[0,0],"ix":1},"s":{"a":0,"k":[100,100],"ix":3},"r":{"a":0,"k":0,"ix":6},"o":{"a":0,"k":100,"ix":7},"sk":{"a":0,"k":0,"ix":4},"sa":{"a":0,"k":0,"ix":5},"nm":"Transform"}],"nm":"Group 1","np":2,"cix":2,"bm":0,"ix":1,"mn":"ADBE Vector Group","hd":false}],"ip":0,"op":1200,"st":0,"bm":0},{"ddd":0,"ind":29,"ty":4,"nm":"Layer 29 Outlines","sr":1,"ks":{"o":{"a":0,"k":100,"ix":11},"r":{"a":0,"k":0,"ix":10},"p":{"a":0,"k":[1048.083,610.145,0],"ix":2},"a":{"a":0,"k":[8.954,10.372,0],"ix":1},"s":{"a":0,"k":[100,100,100],"ix":6}},"ao":0,"shapes":[{"ty":"gr","it":[{"ind":0,"ty":"sh","ix":1,"ks":{"a":0,"k":{"i":[[1.623,-4.346],[3.359,1.255],[-1.623,4.345],[-3.359,-1.254]],"o":[[-1.622,4.345],[-3.359,-1.254],[1.623,-4.346],[3.359,1.255]],"v":[[6.082,2.271],[-2.938,7.867],[-6.082,-2.272],[2.938,-7.868]],"c":true},"ix":2},"nm":"Path 1","mn":"ADBE Vector Shape - Group","hd":false},{"ty":"st","c":{"a":0,"k":[0.361000001197,0.361000001197,0.426999978458,1],"ix":3},"o":{"a":0,"k":100,"ix":4},"w":{"a":0,"k":0.5,"ix":5},"lc":1,"lj":1,"ml":10,"bm":0,"nm":"Stroke 1","mn":"ADBE Vector Graphic - Stroke","hd":false},{"ty":"tr","p":{"a":0,"k":[8.954,10.372],"ix":2},"a":{"a":0,"k":[0,0],"ix":1},"s":{"a":0,"k":[100,100],"ix":3},"r":{"a":0,"k":0,"ix":6},"o":{"a":0,"k":100,"ix":7},"sk":{"a":0,"k":0,"ix":4},"sa":{"a":0,"k":0,"ix":5},"nm":"Transform"}],"nm":"Group 1","np":2,"cix":2,"bm":0,"ix":1,"mn":"ADBE Vector Group","hd":false}],"ip":0,"op":1200,"st":0,"bm":0},{"ddd":0,"ind":30,"ty":4,"nm":"Layer 30 Outlines","sr":1,"ks":{"o":{"a":0,"k":100,"ix":11},"r":{"a":0,"k":0,"ix":10},"p":{"a":0,"k":[1029.926,615.871,0],"ix":2},"a":{"a":0,"k":[8.955,10.373,0],"ix":1},"s":{"a":0,"k":[100,100,100],"ix":6}},"ao":0,"shapes":[{"ty":"gr","it":[{"ind":0,"ty":"sh","ix":1,"ks":{"a":0,"k":{"i":[[1.623,-4.346],[3.359,1.255],[-1.623,4.345],[-3.359,-1.254]],"o":[[-1.623,4.345],[-3.359,-1.254],[1.623,-4.346],[3.359,1.255]],"v":[[6.082,2.271],[-2.939,7.867],[-6.082,-2.272],[2.938,-7.868]],"c":true},"ix":2},"nm":"Path 1","mn":"ADBE Vector Shape - Group","hd":false},{"ty":"st","c":{"a":0,"k":[0.361000001197,0.361000001197,0.426999978458,1],"ix":3},"o":{"a":0,"k":100,"ix":4},"w":{"a":0,"k":0.5,"ix":5},"lc":1,"lj":1,"ml":10,"bm":0,"nm":"Stroke 1","mn":"ADBE Vector Graphic - Stroke","hd":false},{"ty":"tr","p":{"a":0,"k":[8.955,10.373],"ix":2},"a":{"a":0,"k":[0,0],"ix":1},"s":{"a":0,"k":[100,100],"ix":3},"r":{"a":0,"k":0,"ix":6},"o":{"a":0,"k":100,"ix":7},"sk":{"a":0,"k":0,"ix":4},"sa":{"a":0,"k":0,"ix":5},"nm":"Transform"}],"nm":"Group 1","np":2,"cix":2,"bm":0,"ix":1,"mn":"ADBE Vector Group","hd":false}],"ip":0,"op":1200,"st":0,"bm":0},{"ddd":0,"ind":31,"ty":4,"nm":"Layer 31 Outlines","sr":1,"ks":{"o":{"a":0,"k":100,"ix":11},"r":{"a":0,"k":0,"ix":10},"p":{"a":0,"k":[1007.158,621.598,0],"ix":2},"a":{"a":0,"k":[8.955,10.372,0],"ix":1},"s":{"a":0,"k":[100,100,100],"ix":6}},"ao":0,"shapes":[{"ty":"gr","it":[{"ind":0,"ty":"sh","ix":1,"ks":{"a":0,"k":{"i":[[1.623,-4.346],[3.36,1.255],[-1.622,4.345],[-3.358,-1.254]],"o":[[-1.623,4.345],[-3.358,-1.254],[1.623,-4.346],[3.36,1.255]],"v":[[6.082,2.271],[-2.94,7.867],[-6.082,-2.272],[2.937,-7.868]],"c":true},"ix":2},"nm":"Path 1","mn":"ADBE Vector Shape - Group","hd":false},{"ty":"st","c":{"a":0,"k":[0.361000001197,0.361000001197,0.426999978458,1],"ix":3},"o":{"a":0,"k":100,"ix":4},"w":{"a":0,"k":0.5,"ix":5},"lc":1,"lj":1,"ml":10,"bm":0,"nm":"Stroke 1","mn":"ADBE Vector Graphic - Stroke","hd":false},{"ty":"tr","p":{"a":0,"k":[8.955,10.373],"ix":2},"a":{"a":0,"k":[0,0],"ix":1},"s":{"a":0,"k":[100,100],"ix":3},"r":{"a":0,"k":0,"ix":6},"o":{"a":0,"k":100,"ix":7},"sk":{"a":0,"k":0,"ix":4},"sa":{"a":0,"k":0,"ix":5},"nm":"Transform"}],"nm":"Group 1","np":2,"cix":2,"bm":0,"ix":1,"mn":"ADBE Vector Group","hd":false}],"ip":0,"op":1200,"st":0,"bm":0},{"ddd":0,"ind":32,"ty":4,"nm":"Layer 32 Outlines","sr":1,"ks":{"o":{"a":0,"k":100,"ix":11},"r":{"a":0,"k":0,"ix":10},"p":{"a":0,"k":[984.389,627.324,0],"ix":2},"a":{"a":0,"k":[8.955,10.372,0],"ix":1},"s":{"a":0,"k":[100,100,100],"ix":6}},"ao":0,"shapes":[{"ty":"gr","it":[{"ind":0,"ty":"sh","ix":1,"ks":{"a":0,"k":{"i":[[1.623,-4.346],[3.359,1.255],[-1.623,4.345],[-3.359,-1.254]],"o":[[-1.622,4.345],[-3.359,-1.254],[1.623,-4.346],[3.359,1.255]],"v":[[6.082,2.271],[-2.939,7.867],[-6.082,-2.272],[2.939,-7.868]],"c":true},"ix":2},"nm":"Path 1","mn":"ADBE Vector Shape - Group","hd":false},{"ty":"st","c":{"a":0,"k":[0.361000001197,0.361000001197,0.426999978458,1],"ix":3},"o":{"a":0,"k":100,"ix":4},"w":{"a":0,"k":0.5,"ix":5},"lc":1,"lj":1,"ml":10,"bm":0,"nm":"Stroke 1","mn":"ADBE Vector Graphic - Stroke","hd":false},{"ty":"tr","p":{"a":0,"k":[8.954,10.373],"ix":2},"a":{"a":0,"k":[0,0],"ix":1},"s":{"a":0,"k":[100,100],"ix":3},"r":{"a":0,"k":0,"ix":6},"o":{"a":0,"k":100,"ix":7},"sk":{"a":0,"k":0,"ix":4},"sa":{"a":0,"k":0,"ix":5},"nm":"Transform"}],"nm":"Group 1","np":2,"cix":2,"bm":0,"ix":1,"mn":"ADBE Vector Group","hd":false}],"ip":0,"op":1200,"st":0,"bm":0},{"ddd":0,"ind":33,"ty":4,"nm":"Layer 33 Outlines","sr":1,"ks":{"o":{"a":0,"k":100,"ix":11},"r":{"a":0,"k":0,"ix":10},"p":{"a":0,"k":[776.241,518.993,0],"ix":2},"a":{"a":0,"k":[36.965,27.349,0],"ix":1},"s":{"a":0,"k":[100,100,100],"ix":6}},"ao":0,"shapes":[{"ty":"gr","it":[{"ind":0,"ty":"sh","ix":1,"ks":{"a":0,"k":{"i":[[0,0],[0,0],[1.623,-11.708],[0,0]],"o":[[0,0],[0,0],[0,0],[0,0]],"v":[[-12.181,-19.953],[-23.137,-26.099],[-35.715,-14.272],[35.715,26.099]],"c":false},"ix":2},"nm":"Path 1","mn":"ADBE Vector Shape - Group","hd":false},{"ty":"st","c":{"a":0,"k":[0.361000001197,0.361000001197,0.426999978458,1],"ix":3},"o":{"a":0,"k":100,"ix":4},"w":{"a":0,"k":0.5,"ix":5},"lc":1,"lj":1,"ml":10,"bm":0,"nm":"Stroke 1","mn":"ADBE Vector Graphic - Stroke","hd":false},{"ty":"tr","p":{"a":0,"k":[36.965,27.349],"ix":2},"a":{"a":0,"k":[0,0],"ix":1},"s":{"a":0,"k":[100,100],"ix":3},"r":{"a":0,"k":0,"ix":6},"o":{"a":0,"k":100,"ix":7},"sk":{"a":0,"k":0,"ix":4},"sa":{"a":0,"k":0,"ix":5},"nm":"Transform"}],"nm":"Group 1","np":2,"cix":2,"bm":0,"ix":1,"mn":"ADBE Vector Group","hd":false}],"ip":0,"op":1200,"st":0,"bm":0},{"ddd":0,"ind":34,"ty":4,"nm":"Layer 34 Outlines","sr":1,"ks":{"o":{"a":0,"k":100,"ix":11},"r":{"a":0,"k":0,"ix":10},"p":{"a":0,"k":[794.592,510.646,0],"ix":2},"a":{"a":0,"k":[31.783,24.157,0],"ix":1},"s":{"a":0,"k":[100,100,100],"ix":6}},"ao":0,"shapes":[{"ty":"gr","it":[{"ind":0,"ty":"sh","ix":1,"ks":{"a":0,"k":{"i":[[0,0],[0,0],[3.246,-11.302],[0,0]],"o":[[0,0],[0,0],[0,0],[0,0]],"v":[[-6.592,-15.198],[-17.549,-21.404],[-30.533,-11.605],[30.533,22.908]],"c":false},"ix":2},"nm":"Path 1","mn":"ADBE Vector Shape - Group","hd":false},{"ty":"st","c":{"a":0,"k":[0.361000001197,0.361000001197,0.426999978458,1],"ix":3},"o":{"a":0,"k":100,"ix":4},"w":{"a":0,"k":0.5,"ix":5},"lc":1,"lj":1,"ml":10,"bm":0,"nm":"Stroke 1","mn":"ADBE Vector Graphic - Stroke","hd":false},{"ty":"tr","p":{"a":0,"k":[31.783,24.158],"ix":2},"a":{"a":0,"k":[0,0],"ix":1},"s":{"a":0,"k":[100,100],"ix":3},"r":{"a":0,"k":0,"ix":6},"o":{"a":0,"k":100,"ix":7},"sk":{"a":0,"k":0,"ix":4},"sa":{"a":0,"k":0,"ix":5},"nm":"Transform"}],"nm":"Group 1","np":2,"cix":2,"bm":0,"ix":1,"mn":"ADBE Vector Group","hd":false}],"ip":0,"op":1200,"st":0,"bm":0},{"ddd":0,"ind":35,"ty":4,"nm":"Layer 35 Outlines","sr":1,"ks":{"o":{"a":0,"k":100,"ix":11},"r":{"a":0,"k":0,"ix":10},"p":{"a":0,"k":[818.88,505.198,0],"ix":2},"a":{"a":0,"k":[32.131,24.271,0],"ix":1},"s":{"a":0,"k":[100,100,100],"ix":6}},"ao":0,"shapes":[{"ty":"gr","it":[{"ind":0,"ty":"sh","ix":1,"ks":{"a":0,"k":{"i":[[0,0],[0,0],[2.029,-13.271],[0,0]],"o":[[0,0],[0,0],[0,0],[0,0]],"v":[[-8.952,-14.333],[-18.642,-19.608],[-30.88,-9.75],[30.88,23.021]],"c":false},"ix":2},"nm":"Path 1","mn":"ADBE Vector Shape - Group","hd":false},{"ty":"st","c":{"a":0,"k":[0.361000001197,0.361000001197,0.426999978458,1],"ix":3},"o":{"a":0,"k":100,"ix":4},"w":{"a":0,"k":0.5,"ix":5},"lc":1,"lj":1,"ml":10,"bm":0,"nm":"Stroke 1","mn":"ADBE Vector Graphic - Stroke","hd":false},{"ty":"tr","p":{"a":0,"k":[32.13,24.271],"ix":2},"a":{"a":0,"k":[0,0],"ix":1},"s":{"a":0,"k":[100,100],"ix":3},"r":{"a":0,"k":0,"ix":6},"o":{"a":0,"k":100,"ix":7},"sk":{"a":0,"k":0,"ix":4},"sa":{"a":0,"k":0,"ix":5},"nm":"Transform"}],"nm":"Group 1","np":2,"cix":2,"bm":0,"ix":1,"mn":"ADBE Vector Group","hd":false}],"ip":0,"op":1200,"st":0,"bm":0},{"ddd":0,"ind":36,"ty":4,"nm":"Layer 36 Outlines","sr":1,"ks":{"o":{"a":0,"k":100,"ix":11},"r":{"a":0,"k":0,"ix":10},"p":{"a":0,"k":[840.651,500.912,0],"ix":2},"a":{"a":0,"k":[31.974,24.282,0],"ix":1},"s":{"a":0,"k":[100,100,100],"ix":6}},"ao":0,"shapes":[{"ty":"gr","it":[{"ind":0,"ty":"sh","ix":1,"ks":{"a":0,"k":{"i":[[0,0],[0,0],[4.885,-12.985],[0,0]],"o":[[0,0],[0,0],[0,0],[0,0]],"v":[[-8.423,-13.699],[-16.539,-17.757],[-30.724,-10.047],[30.724,23.031]],"c":false},"ix":2},"nm":"Path 1","mn":"ADBE Vector Shape - Group","hd":false},{"ty":"st","c":{"a":0,"k":[0.361000001197,0.361000001197,0.426999978458,1],"ix":3},"o":{"a":0,"k":100,"ix":4},"w":{"a":0,"k":0.5,"ix":5},"lc":1,"lj":1,"ml":10,"bm":0,"nm":"Stroke 1","mn":"ADBE Vector Graphic - Stroke","hd":false},{"ty":"tr","p":{"a":0,"k":[31.973,24.282],"ix":2},"a":{"a":0,"k":[0,0],"ix":1},"s":{"a":0,"k":[100,100],"ix":3},"r":{"a":0,"k":0,"ix":6},"o":{"a":0,"k":100,"ix":7},"sk":{"a":0,"k":0,"ix":4},"sa":{"a":0,"k":0,"ix":5},"nm":"Transform"}],"nm":"Group 1","np":2,"cix":2,"bm":0,"ix":1,"mn":"ADBE Vector Group","hd":false}],"ip":0,"op":1200,"st":0,"bm":0},{"ddd":0,"ind":37,"ty":4,"nm":"Layer 37 Outlines","sr":1,"ks":{"o":{"a":0,"k":100,"ix":11},"r":{"a":0,"k":0,"ix":10},"p":{"a":0,"k":[862.989,497.482,0],"ix":2},"a":{"a":0,"k":[32.011,23.286,0],"ix":1},"s":{"a":0,"k":[100,100,100],"ix":6}},"ao":0,"shapes":[{"ty":"gr","it":[{"ind":0,"ty":"sh","ix":1,"ks":{"a":0,"k":{"i":[[0,0],[0,0],[4.057,-11.767],[0,0]],"o":[[0,0],[0,0],[0,0],[0,0]],"v":[[-8.85,-13.109],[-19.4,-18.384],[-30.761,-10.269],[30.761,22.036]],"c":false},"ix":2},"nm":"Path 1","mn":"ADBE Vector Shape - Group","hd":false},{"ty":"st","c":{"a":0,"k":[0.361000001197,0.361000001197,0.426999978458,1],"ix":3},"o":{"a":0,"k":100,"ix":4},"w":{"a":0,"k":0.5,"ix":5},"lc":1,"lj":1,"ml":10,"bm":0,"nm":"Stroke 1","mn":"ADBE Vector Graphic - Stroke","hd":false},{"ty":"tr","p":{"a":0,"k":[32.011,23.286],"ix":2},"a":{"a":0,"k":[0,0],"ix":1},"s":{"a":0,"k":[100,100],"ix":3},"r":{"a":0,"k":0,"ix":6},"o":{"a":0,"k":100,"ix":7},"sk":{"a":0,"k":0,"ix":4},"sa":{"a":0,"k":0,"ix":5},"nm":"Transform"}],"nm":"Group 1","np":2,"cix":2,"bm":0,"ix":1,"mn":"ADBE Vector Group","hd":false}],"ip":0,"op":1200,"st":0,"bm":0},{"ddd":0,"ind":38,"ty":4,"nm":"Layer 38 Outlines","sr":1,"ks":{"o":{"a":0,"k":100,"ix":11},"r":{"a":0,"k":0,"ix":10},"p":{"a":0,"k":[893.75,494.513,0],"ix":2},"a":{"a":0,"k":[40.861,21.939,0],"ix":1},"s":{"a":0,"k":[100,100,100],"ix":6}},"ao":0,"shapes":[{"ty":"gr","it":[{"ind":0,"ty":"sh","ix":1,"ks":{"a":0,"k":{"i":[[0,0],[0,0],[1.623,-10.549],[0,0]],"o":[[0,0],[0,0],[0,0],[0,0]],"v":[[39.611,17.17],[-31.495,-18.661],[-39.611,-10.14],[21.822,20.689]],"c":false},"ix":2},"nm":"Path 1","mn":"ADBE Vector Shape - Group","hd":false},{"ty":"st","c":{"a":0,"k":[0.361000001197,0.361000001197,0.426999978458,1],"ix":3},"o":{"a":0,"k":100,"ix":4},"w":{"a":0,"k":0.5,"ix":5},"lc":1,"lj":1,"ml":10,"bm":0,"nm":"Stroke 1","mn":"ADBE Vector Graphic - Stroke","hd":false},{"ty":"tr","p":{"a":0,"k":[40.861,21.939],"ix":2},"a":{"a":0,"k":[0,0],"ix":1},"s":{"a":0,"k":[100,100],"ix":3},"r":{"a":0,"k":0,"ix":6},"o":{"a":0,"k":100,"ix":7},"sk":{"a":0,"k":0,"ix":4},"sa":{"a":0,"k":0,"ix":5},"nm":"Transform"}],"nm":"Group 1","np":2,"cix":2,"bm":0,"ix":1,"mn":"ADBE Vector Group","hd":false}],"ip":0,"op":1200,"st":0,"bm":0},{"ddd":0,"ind":39,"ty":4,"nm":"Layer 40 Outlines","sr":1,"ks":{"o":{"a":0,"k":100,"ix":11},"r":{"a":0,"k":0,"ix":10},"p":{"a":0,"k":[729.165,505.676,0],"ix":2},"a":{"a":0,"k":[11.611,2.481,0],"ix":1},"s":{"a":0,"k":[100,100,100],"ix":6}},"ao":0,"shapes":[{"ty":"gr","it":[{"ind":0,"ty":"sh","ix":1,"ks":{"a":0,"k":{"i":[[0,0],[0,0]],"o":[[0,0],[0,0]],"v":[[-11.361,2.231],[11.361,-2.231]],"c":false},"ix":2},"nm":"Path 1","mn":"ADBE Vector Shape - Group","hd":false},{"ty":"st","c":{"a":0,"k":[0.361000001197,0.361000001197,0.426999978458,1],"ix":3},"o":{"a":0,"k":100,"ix":4},"w":{"a":0,"k":0.5,"ix":5},"lc":1,"lj":1,"ml":10,"bm":0,"nm":"Stroke 1","mn":"ADBE Vector Graphic - Stroke","hd":false},{"ty":"tr","p":{"a":0,"k":[11.611,2.482],"ix":2},"a":{"a":0,"k":[0,0],"ix":1},"s":{"a":0,"k":[100,100],"ix":3},"r":{"a":0,"k":0,"ix":6},"o":{"a":0,"k":100,"ix":7},"sk":{"a":0,"k":0,"ix":4},"sa":{"a":0,"k":0,"ix":5},"nm":"Transform"}],"nm":"Group 1","np":2,"cix":2,"bm":0,"ix":1,"mn":"ADBE Vector Group","hd":false}],"ip":0,"op":1200,"st":0,"bm":0},{"ddd":0,"ind":40,"ty":4,"nm":"Layer 41 Outlines","sr":1,"ks":{"o":{"a":0,"k":100,"ix":11},"r":{"a":0,"k":0,"ix":10},"p":{"a":0,"k":[510.151,394.595,0],"ix":2},"a":{"a":0,"k":[295.121,170.755,0],"ix":1},"s":{"a":0,"k":[100,100,100],"ix":6}},"ao":0,"shapes":[{"ty":"gr","it":[{"ind":0,"ty":"sh","ix":1,"ks":{"a":0,"k":{"i":[[0,0],[0,0],[0,0],[0,0]],"o":[[0,0],[0,0],[0,0],[0,0]],"v":[[293.871,169.504],[205.624,118.993],[207.652,113.313],[-293.871,-169.505]],"c":false},"ix":2},"nm":"Path 1","mn":"ADBE Vector Shape - Group","hd":false},{"ty":"st","c":{"a":0,"k":[0.361000001197,0.361000001197,0.426999978458,1],"ix":3},"o":{"a":0,"k":100,"ix":4},"w":{"a":0,"k":0.5,"ix":5},"lc":1,"lj":1,"ml":10,"bm":0,"nm":"Stroke 1","mn":"ADBE Vector Graphic - Stroke","hd":false},{"ty":"tr","p":{"a":0,"k":[295.121,170.755],"ix":2},"a":{"a":0,"k":[0,0],"ix":1},"s":{"a":0,"k":[100,100],"ix":3},"r":{"a":0,"k":0,"ix":6},"o":{"a":0,"k":100,"ix":7},"sk":{"a":0,"k":0,"ix":4},"sa":{"a":0,"k":0,"ix":5},"nm":"Transform"}],"nm":"Group 1","np":2,"cix":2,"bm":0,"ix":1,"mn":"ADBE Vector Group","hd":false}],"ip":0,"op":1200,"st":0,"bm":0},{"ddd":0,"ind":41,"ty":4,"nm":"Layer 42 Outlines","sr":1,"ks":{"o":{"a":0,"k":100,"ix":11},"r":{"a":0,"k":0,"ix":10},"p":{"a":0,"k":[499.332,405.255,0],"ix":2},"a":{"a":0,"k":[301.155,174.329,0],"ix":1},"s":{"a":0,"k":[100,100,100],"ix":6}},"ao":0,"shapes":[{"ty":"gr","it":[{"ind":0,"ty":"sh","ix":1,"ks":{"a":0,"k":{"i":[[0,0],[0,0]],"o":[[0,0],[0,0]],"v":[[300.905,174.079],[-300.905,-174.079]],"c":false},"ix":2},"nm":"Path 1","mn":"ADBE Vector Shape - Group","hd":false},{"ty":"st","c":{"a":0,"k":[0.361000001197,0.361000001197,0.426999978458,1],"ix":3},"o":{"a":0,"k":100,"ix":4},"w":{"a":0,"k":0.5,"ix":5},"lc":1,"lj":1,"ml":10,"bm":0,"nm":"Stroke 1","mn":"ADBE Vector Graphic - Stroke","hd":false},{"ty":"tr","p":{"a":0,"k":[301.155,174.329],"ix":2},"a":{"a":0,"k":[0,0],"ix":1},"s":{"a":0,"k":[100,100],"ix":3},"r":{"a":0,"k":0,"ix":6},"o":{"a":0,"k":100,"ix":7},"sk":{"a":0,"k":0,"ix":4},"sa":{"a":0,"k":0,"ix":5},"nm":"Transform"}],"nm":"Group 1","np":2,"cix":2,"bm":0,"ix":1,"mn":"ADBE Vector Group","hd":false}],"ip":0,"op":1200,"st":0,"bm":0},{"ddd":0,"ind":42,"ty":4,"nm":"Layer 44 Outlines","sr":1,"ks":{"o":{"a":0,"k":100,"ix":11},"r":{"a":0,"k":0,"ix":10},"p":{"a":0,"k":[1247.636,804.09,0],"ix":2},"a":{"a":0,"k":[373.427,199.693,0],"ix":1},"s":{"a":0,"k":[100,100,100],"ix":6}},"ao":0,"shapes":[{"ty":"gr","it":[{"ind":0,"ty":"sh","ix":1,"ks":{"a":0,"k":{"i":[[0,0],[0,0],[-3.246,1.218],[0,0],[-16.23,26.781]],"o":[[0,0],[0,0],[3.246,-1.216],[0,0],[0,0]],"v":[[-372.177,-198.443],[264.245,157.866],[276.418,160.705],[329.978,187.08],[372.177,171.661]],"c":false},"ix":2},"nm":"Path 1","mn":"ADBE Vector Shape - Group","hd":false},{"ty":"st","c":{"a":0,"k":[0.361000001197,0.361000001197,0.426999978458,1],"ix":3},"o":{"a":0,"k":100,"ix":4},"w":{"a":0,"k":0.5,"ix":5},"lc":1,"lj":1,"ml":10,"bm":0,"nm":"Stroke 1","mn":"ADBE Vector Graphic - Stroke","hd":false},{"ty":"tr","p":{"a":0,"k":[373.427,199.693],"ix":2},"a":{"a":0,"k":[0,0],"ix":1},"s":{"a":0,"k":[100,100],"ix":3},"r":{"a":0,"k":0,"ix":6},"o":{"a":0,"k":100,"ix":7},"sk":{"a":0,"k":0,"ix":4},"sa":{"a":0,"k":0,"ix":5},"nm":"Transform"}],"nm":"Group 1","np":2,"cix":2,"bm":0,"ix":1,"mn":"ADBE Vector Group","hd":false}],"ip":0,"op":1200,"st":0,"bm":0},{"ddd":0,"ind":43,"ty":4,"nm":"Layer 45 Outlines","sr":1,"ks":{"o":{"a":0,"k":100,"ix":11},"r":{"a":0,"k":0,"ix":10},"p":{"a":0,"k":[899.575,586.341,0],"ix":2},"a":{"a":0,"k":[74.277,60.918,0],"ix":1},"s":{"a":0,"k":[100,100,100],"ix":6}},"ao":0,"shapes":[{"ty":"gr","it":[{"ind":0,"ty":"sh","ix":1,"ks":{"a":0,"k":{"i":[[0,0],[-4.058,16.069],[0,0],[-8.927,1.217],[0,0]],"o":[[0,0],[4.057,-16.07],[0,0],[8.927,-1.217],[0,0]],"v":[[-66.213,59.667],[-68.97,32.178],[-54.769,-18.68],[-41.783,-35.018],[73.027,-59.667]],"c":false},"ix":2},"nm":"Path 1","mn":"ADBE Vector Shape - Group","hd":false},{"ty":"st","c":{"a":0,"k":[0.361000001197,0.361000001197,0.426999978458,1],"ix":3},"o":{"a":0,"k":100,"ix":4},"w":{"a":0,"k":0.5,"ix":5},"lc":1,"lj":1,"ml":10,"bm":0,"nm":"Stroke 1","mn":"ADBE Vector Graphic - Stroke","hd":false},{"ty":"tr","p":{"a":0,"k":[74.277,60.918],"ix":2},"a":{"a":0,"k":[0,0],"ix":1},"s":{"a":0,"k":[100,100],"ix":3},"r":{"a":0,"k":0,"ix":6},"o":{"a":0,"k":100,"ix":7},"sk":{"a":0,"k":0,"ix":4},"sa":{"a":0,"k":0,"ix":5},"nm":"Transform"}],"nm":"Group 1","np":2,"cix":2,"bm":0,"ix":1,"mn":"ADBE Vector Group","hd":false}],"ip":0,"op":1200,"st":0,"bm":0},{"ddd":0,"ind":44,"ty":4,"nm":"Layer 46 Outlines","sr":1,"ks":{"o":{"a":0,"k":100,"ix":11},"r":{"a":0,"k":0,"ix":10},"p":{"a":0,"k":[903.792,567.663,0],"ix":2},"a":{"a":0,"k":[111.468,58.977,0],"ix":1},"s":{"a":0,"k":[100,100,100],"ix":6}},"ao":0,"shapes":[{"ty":"gr","it":[{"ind":0,"ty":"sh","ix":1,"ks":{"a":0,"k":{"i":[[0,0],[12.985,6.086],[0,0],[0,0],[6.492,-16.231],[0.824,-1.909],[1.276,-6.517],[0,0],[-4.923,-10.741]],"o":[[0,0],[-12.984,-6.087],[0,0],[0,0],[-1.277,3.193],[-2.633,6.096],[0,0],[0,0],[0,0]],"v":[[108.501,-17.17],[97.233,-26.077],[38.398,-57.726],[-72.375,-35.816],[-93.881,-18.368],[-97.008,-10.794],[-102.871,8.182],[-108.082,34.787],[-105.295,57.726]],"c":false},"ix":2},"nm":"Path 1","mn":"ADBE Vector Shape - Group","hd":false},{"ty":"st","c":{"a":0,"k":[0.361000001197,0.361000001197,0.426999978458,1],"ix":3},"o":{"a":0,"k":100,"ix":4},"w":{"a":0,"k":0.5,"ix":5},"lc":1,"lj":1,"ml":10,"bm":0,"nm":"Stroke 1","mn":"ADBE Vector Graphic - Stroke","hd":false},{"ty":"tr","p":{"a":0,"k":[111.468,58.977],"ix":2},"a":{"a":0,"k":[0,0],"ix":1},"s":{"a":0,"k":[100,100],"ix":3},"r":{"a":0,"k":0,"ix":6},"o":{"a":0,"k":100,"ix":7},"sk":{"a":0,"k":0,"ix":4},"sa":{"a":0,"k":0,"ix":5},"nm":"Transform"}],"nm":"Group 1","np":2,"cix":2,"bm":0,"ix":1,"mn":"ADBE Vector Group","hd":false}],"ip":0,"op":1200,"st":0,"bm":0},{"ddd":0,"ind":45,"ty":4,"nm":"Layer 47 Outlines","sr":1,"ks":{"o":{"a":0,"k":100,"ix":11},"r":{"a":0,"k":0,"ix":10},"p":{"a":0,"k":[932.046,604.087,0],"ix":2},"a":{"a":0,"k":[70.23,63.751,0],"ix":1},"s":{"a":0,"k":[100,100,100],"ix":6}},"ao":0,"shapes":[{"ty":"gr","it":[{"ind":0,"ty":"sh","ix":1,"ks":{"a":0,"k":{"i":[[0,0],[-4.463,22.723],[0,0],[-6.898,1.217],[0,0]],"o":[[0,0],[4.463,-22.722],[0,0],[6.898,-1.217],[0,0]],"v":[[-63.887,62.501],[-64.517,30.824],[-47.881,-23.144],[-39.36,-32.476],[68.98,-62.501]],"c":false},"ix":2},"nm":"Path 1","mn":"ADBE Vector Shape - Group","hd":false},{"ty":"st","c":{"a":0,"k":[0.361000001197,0.361000001197,0.426999978458,1],"ix":3},"o":{"a":0,"k":100,"ix":4},"w":{"a":0,"k":0.5,"ix":5},"lc":1,"lj":1,"ml":10,"bm":0,"nm":"Stroke 1","mn":"ADBE Vector Graphic - Stroke","hd":false},{"ty":"tr","p":{"a":0,"k":[70.229,63.752],"ix":2},"a":{"a":0,"k":[0,0],"ix":1},"s":{"a":0,"k":[100,100],"ix":3},"r":{"a":0,"k":0,"ix":6},"o":{"a":0,"k":100,"ix":7},"sk":{"a":0,"k":0,"ix":4},"sa":{"a":0,"k":0,"ix":5},"nm":"Transform"}],"nm":"Group 1","np":2,"cix":2,"bm":0,"ix":1,"mn":"ADBE Vector Group","hd":false}],"ip":0,"op":1200,"st":0,"bm":0},{"ddd":0,"ind":46,"ty":4,"nm":"Layer 48 Outlines","sr":1,"ks":{"o":{"a":0,"k":100,"ix":11},"r":{"a":0,"k":0,"ix":10},"p":{"a":0,"k":[939.989,865.237,0],"ix":2},"a":{"a":0,"k":[31.619,36.857,0],"ix":1},"s":{"a":0,"k":[100,100,100],"ix":6}},"ao":0,"shapes":[{"ty":"gr","it":[{"ind":0,"ty":"sh","ix":1,"ks":{"a":0,"k":{"i":[[0,0],[0,0]],"o":[[0,0],[0,0]],"v":[[-31.369,36.607],[31.369,-36.607]],"c":false},"ix":2},"nm":"Path 1","mn":"ADBE Vector Shape - Group","hd":false},{"ty":"st","c":{"a":0,"k":[0.361000001197,0.361000001197,0.426999978458,1],"ix":3},"o":{"a":0,"k":100,"ix":4},"w":{"a":0,"k":0.5,"ix":5},"lc":1,"lj":1,"ml":10,"bm":0,"nm":"Stroke 1","mn":"ADBE Vector Graphic - Stroke","hd":false},{"ty":"tr","p":{"a":0,"k":[31.619,36.857],"ix":2},"a":{"a":0,"k":[0,0],"ix":1},"s":{"a":0,"k":[100,100],"ix":3},"r":{"a":0,"k":0,"ix":6},"o":{"a":0,"k":100,"ix":7},"sk":{"a":0,"k":0,"ix":4},"sa":{"a":0,"k":0,"ix":5},"nm":"Transform"}],"nm":"Group 1","np":2,"cix":2,"bm":0,"ix":1,"mn":"ADBE Vector Group","hd":false}],"ip":0,"op":1200,"st":0,"bm":0},{"ddd":0,"ind":47,"ty":4,"nm":"Layer 49 Outlines","sr":1,"ks":{"o":{"a":0,"k":100,"ix":11},"r":{"a":0,"k":0,"ix":10},"p":{"a":0,"k":[984.107,787.783,0],"ix":2},"a":{"a":0,"k":[16.545,52.459,0],"ix":1},"s":{"a":0,"k":[100,100,100],"ix":6}},"ao":0,"shapes":[{"ty":"gr","it":[{"ind":0,"ty":"sh","ix":1,"ks":{"a":0,"k":{"i":[[0,0],[0,0]],"o":[[0,0],[0,0]],"v":[[16.295,-52.209],[-16.295,52.209]],"c":false},"ix":2},"nm":"Path 1","mn":"ADBE Vector Shape - Group","hd":false},{"ty":"st","c":{"a":0,"k":[0.361000001197,0.361000001197,0.426999978458,1],"ix":3},"o":{"a":0,"k":100,"ix":4},"w":{"a":0,"k":0.5,"ix":5},"lc":1,"lj":1,"ml":10,"bm":0,"nm":"Stroke 1","mn":"ADBE Vector Graphic - Stroke","hd":false},{"ty":"tr","p":{"a":0,"k":[16.545,52.459],"ix":2},"a":{"a":0,"k":[0,0],"ix":1},"s":{"a":0,"k":[100,100],"ix":3},"r":{"a":0,"k":0,"ix":6},"o":{"a":0,"k":100,"ix":7},"sk":{"a":0,"k":0,"ix":4},"sa":{"a":0,"k":0,"ix":5},"nm":"Transform"}],"nm":"Group 1","np":2,"cix":2,"bm":0,"ix":1,"mn":"ADBE Vector Group","hd":false}],"ip":0,"op":1200,"st":0,"bm":0},{"ddd":0,"ind":48,"ty":4,"nm":"Layer 51 Outlines","sr":1,"ks":{"o":{"a":0,"k":100,"ix":11},"r":{"a":0,"k":0,"ix":10},"p":{"a":0,"k":[1331.945,991.863,0],"ix":2},"a":{"a":0,"k":[424.574,263.059,0],"ix":1},"s":{"a":0,"k":[100,100,100],"ix":6}},"ao":0,"shapes":[{"ty":"gr","it":[{"ind":0,"ty":"sh","ix":1,"ks":{"a":0,"k":{"i":[[0,0],[0,0],[4.73,-8.845],[0,0],[0,0],[0,0]],"o":[[0,0],[0,0],[-4.265,7.978],[0,0],[0,0],[0,0]],"v":[[423.325,184.66],[-331.543,-256.289],[-342.186,-252.964],[-403.373,-148.546],[-423.324,-90.019],[-187.221,261.809]],"c":false},"ix":2},"nm":"Path 1","mn":"ADBE Vector Shape - Group","hd":false},{"ty":"st","c":{"a":0,"k":[0.361000001197,0.361000001197,0.426999978458,1],"ix":3},"o":{"a":0,"k":100,"ix":4},"w":{"a":0,"k":0.5,"ix":5},"lc":1,"lj":1,"ml":10,"bm":0,"nm":"Stroke 1","mn":"ADBE Vector Graphic - Stroke","hd":false},{"ty":"tr","p":{"a":0,"k":[424.575,263.059],"ix":2},"a":{"a":0,"k":[0,0],"ix":1},"s":{"a":0,"k":[100,100],"ix":3},"r":{"a":0,"k":0,"ix":6},"o":{"a":0,"k":100,"ix":7},"sk":{"a":0,"k":0,"ix":4},"sa":{"a":0,"k":0,"ix":5},"nm":"Transform"}],"nm":"Group 1","np":2,"cix":2,"bm":0,"ix":1,"mn":"ADBE Vector Group","hd":false}],"ip":0,"op":1200,"st":0,"bm":0},{"ddd":0,"ind":49,"ty":4,"nm":"Layer 52 Outlines","sr":1,"ks":{"o":{"a":0,"k":100,"ix":11},"r":{"a":0,"k":0,"ix":10},"p":{"a":0,"k":[1280.515,1038.851,0],"ix":2},"a":{"a":0,"k":[328.356,200.109,0],"ix":1},"s":{"a":0,"k":[100,100,100],"ix":6}},"ao":0,"shapes":[{"ty":"gr","it":[{"ind":0,"ty":"sh","ix":1,"ks":{"a":0,"k":{"i":[[0,0],[0,0],[0,0],[0,0]],"o":[[0,0],[0,0],[0,0],[0,0]],"v":[[-70.829,169.53],[-327.106,-182.003],[-312.703,-198.859],[327.106,198.859]],"c":false},"ix":2},"nm":"Path 1","mn":"ADBE Vector Shape - Group","hd":false},{"ty":"st","c":{"a":0,"k":[0.361000001197,0.361000001197,0.426999978458,1],"ix":3},"o":{"a":0,"k":100,"ix":4},"w":{"a":0,"k":0.5,"ix":5},"lc":1,"lj":1,"ml":10,"bm":0,"nm":"Stroke 1","mn":"ADBE Vector Graphic - Stroke","hd":false},{"ty":"tr","p":{"a":0,"k":[328.356,200.109],"ix":2},"a":{"a":0,"k":[0,0],"ix":1},"s":{"a":0,"k":[100,100],"ix":3},"r":{"a":0,"k":0,"ix":6},"o":{"a":0,"k":100,"ix":7},"sk":{"a":0,"k":0,"ix":4},"sa":{"a":0,"k":0,"ix":5},"nm":"Transform"}],"nm":"Group 1","np":2,"cix":2,"bm":0,"ix":1,"mn":"ADBE Vector Group","hd":false}],"ip":0,"op":1200,"st":0,"bm":0},{"ddd":0,"ind":50,"ty":4,"nm":"Layer 53 Outlines","sr":1,"ks":{"o":{"a":0,"k":100,"ix":11},"r":{"a":0,"k":0,"ix":10},"p":{"a":0,"k":[1286.799,1045.169,0],"ix":2},"a":{"a":0,"k":[442.612,378.684,0],"ix":1},"s":{"a":0,"k":[100,100,100],"ix":6}},"ao":0,"shapes":[{"ty":"gr","it":[{"ind":0,"ty":"sh","ix":1,"ks":{"a":0,"k":{"i":[[0,0],[0,0],[0,0],[0,0],[-7.316,-11.305],[0,0]],"o":[[0,0],[0,0],[0,0],[0,0],[7.316,11.307],[0,0]],"v":[[441.362,57.745],[-334.284,-377.434],[-405.448,-269.025],[-440.032,-165.938],[-434.046,-150.641],[-102.835,377.434]],"c":false},"ix":2},"nm":"Path 1","mn":"ADBE Vector Shape - Group","hd":false},{"ty":"st","c":{"a":0,"k":[0.361000001197,0.361000001197,0.426999978458,1],"ix":3},"o":{"a":0,"k":100,"ix":4},"w":{"a":0,"k":0.5,"ix":5},"lc":1,"lj":1,"ml":10,"bm":0,"nm":"Stroke 1","mn":"ADBE Vector Graphic - Stroke","hd":false},{"ty":"tr","p":{"a":0,"k":[442.612,378.684],"ix":2},"a":{"a":0,"k":[0,0],"ix":1},"s":{"a":0,"k":[100,100],"ix":3},"r":{"a":0,"k":0,"ix":6},"o":{"a":0,"k":100,"ix":7},"sk":{"a":0,"k":0,"ix":4},"sa":{"a":0,"k":0,"ix":5},"nm":"Transform"}],"nm":"Group 1","np":2,"cix":2,"bm":0,"ix":1,"mn":"ADBE Vector Group","hd":false}],"ip":0,"op":1200,"st":0,"bm":0},{"ddd":0,"ind":51,"ty":4,"nm":"Layer 54 Outlines","sr":1,"ks":{"o":{"a":0,"k":100,"ix":11},"r":{"a":0,"k":0,"ix":10},"p":{"a":0,"k":[1294.368,855.622,0],"ix":2},"a":{"a":0,"k":[423.242,237.352,0],"ix":1},"s":{"a":0,"k":[100,100,100],"ix":6}},"ao":0,"shapes":[{"ty":"gr","it":[{"ind":0,"ty":"sh","ix":1,"ks":{"a":0,"k":{"i":[[0,0],[0,0]],"o":[[0,0],[0,0]],"v":[[-422.992,-237.102],[422.992,237.102]],"c":false},"ix":2},"nm":"Path 1","mn":"ADBE Vector Shape - Group","hd":false},{"ty":"st","c":{"a":0,"k":[0.361000001197,0.361000001197,0.426999978458,1],"ix":3},"o":{"a":0,"k":100,"ix":4},"w":{"a":0,"k":0.5,"ix":5},"lc":1,"lj":1,"ml":10,"bm":0,"nm":"Stroke 1","mn":"ADBE Vector Graphic - Stroke","hd":false},{"ty":"tr","p":{"a":0,"k":[423.242,237.352],"ix":2},"a":{"a":0,"k":[0,0],"ix":1},"s":{"a":0,"k":[100,100],"ix":3},"r":{"a":0,"k":0,"ix":6},"o":{"a":0,"k":100,"ix":7},"sk":{"a":0,"k":0,"ix":4},"sa":{"a":0,"k":0,"ix":5},"nm":"Transform"}],"nm":"Group 1","np":2,"cix":2,"bm":0,"ix":1,"mn":"ADBE Vector Group","hd":false},{"ty":"gr","it":[{"ind":0,"ty":"sh","ix":1,"ks":{"a":0,"k":{"i":[[0,0],[0,0]],"o":[[0,0],[0,0]],"v":[[411.643,230.74],[-411.643,-230.74]],"c":true},"ix":2},"nm":"Path 1","mn":"ADBE Vector Shape - Group","hd":false},{"ty":"fl","c":{"a":0,"k":[1,1,1,1],"ix":4},"o":{"a":0,"k":100,"ix":5},"r":1,"bm":0,"nm":"Fill 1","mn":"ADBE Vector Graphic - Fill","hd":false},{"ty":"tr","p":{"a":0,"k":[411.893,230.99],"ix":2},"a":{"a":0,"k":[0,0],"ix":1},"s":{"a":0,"k":[100,100],"ix":3},"r":{"a":0,"k":0,"ix":6},"o":{"a":0,"k":100,"ix":7},"sk":{"a":0,"k":0,"ix":4},"sa":{"a":0,"k":0,"ix":5},"nm":"Transform"}],"nm":"Group 2","np":2,"cix":2,"bm":0,"ix":2,"mn":"ADBE Vector Group","hd":false}],"ip":0,"op":1200,"st":0,"bm":0},{"ddd":0,"ind":52,"ty":4,"nm":"Layer 55 Outlines","sr":1,"ks":{"o":{"a":0,"k":100,"ix":11},"r":{"a":0,"k":0,"ix":10},"p":{"a":0,"k":[623.078,521.639,0],"ix":2},"a":{"a":0,"k":[305.744,180.931,0],"ix":1},"s":{"a":0,"k":[100,100,100],"ix":6}},"ao":0,"shapes":[{"ty":"gr","it":[{"ind":0,"ty":"sh","ix":1,"ks":{"a":0,"k":{"i":[[0,0],[0,0]],"o":[[0,0],[0,0]],"v":[[305.494,180.681],[-305.494,-180.681]],"c":false},"ix":2},"nm":"Path 1","mn":"ADBE Vector Shape - Group","hd":false},{"ty":"st","c":{"a":0,"k":[0.361000001197,0.361000001197,0.426999978458,1],"ix":3},"o":{"a":0,"k":100,"ix":4},"w":{"a":0,"k":0.5,"ix":5},"lc":1,"lj":1,"ml":10,"bm":0,"nm":"Stroke 1","mn":"ADBE Vector Graphic - Stroke","hd":false},{"ty":"fl","c":{"a":0,"k":[1,1,1,1],"ix":4},"o":{"a":0,"k":100,"ix":5},"r":1,"bm":0,"nm":"Fill 1","mn":"ADBE Vector Graphic - Fill","hd":false},{"ty":"tr","p":{"a":0,"k":[305.744,180.931],"ix":2},"a":{"a":0,"k":[0,0],"ix":1},"s":{"a":0,"k":[100,100],"ix":3},"r":{"a":0,"k":0,"ix":6},"o":{"a":0,"k":100,"ix":7},"sk":{"a":0,"k":0,"ix":4},"sa":{"a":0,"k":0,"ix":5},"nm":"Transform"}],"nm":"Group 1","np":3,"cix":2,"bm":0,"ix":1,"mn":"ADBE Vector Group","hd":false}],"ip":0,"op":1200,"st":0,"bm":0},{"ddd":0,"ind":53,"ty":4,"nm":"Layer 56 Outlines","sr":1,"ks":{"o":{"a":0,"k":100,"ix":11},"r":{"a":0,"k":0,"ix":10},"p":{"a":0,"k":[730.751,510.624,0],"ix":2},"a":{"a":0,"k":[15.227,3.214,0],"ix":1},"s":{"a":0,"k":[100,100,100],"ix":6}},"ao":0,"shapes":[{"ty":"gr","it":[{"ind":0,"ty":"sh","ix":1,"ks":{"a":0,"k":{"i":[[0,0],[0,0]],"o":[[0,0],[0,0]],"v":[[-14.977,2.963],[14.977,-2.963]],"c":false},"ix":2},"nm":"Path 1","mn":"ADBE Vector Shape - Group","hd":false},{"ty":"st","c":{"a":0,"k":[0.361000001197,0.361000001197,0.426999978458,1],"ix":3},"o":{"a":0,"k":100,"ix":4},"w":{"a":0,"k":0.5,"ix":5},"lc":1,"lj":1,"ml":10,"bm":0,"nm":"Stroke 1","mn":"ADBE Vector Graphic - Stroke","hd":false},{"ty":"tr","p":{"a":0,"k":[15.227,3.214],"ix":2},"a":{"a":0,"k":[0,0],"ix":1},"s":{"a":0,"k":[100,100],"ix":3},"r":{"a":0,"k":0,"ix":6},"o":{"a":0,"k":100,"ix":7},"sk":{"a":0,"k":0,"ix":4},"sa":{"a":0,"k":0,"ix":5},"nm":"Transform"}],"nm":"Group 1","np":2,"cix":2,"bm":0,"ix":1,"mn":"ADBE Vector Group","hd":false}],"ip":0,"op":1200,"st":0,"bm":0},{"ddd":0,"ind":54,"ty":4,"nm":"Layer 57 Outlines","sr":1,"ks":{"o":{"a":0,"k":100,"ix":11},"r":{"a":0,"k":0,"ix":10},"p":{"a":0,"k":[1351.441,750.027,0],"ix":2},"a":{"a":0,"k":[245.222,128.679,0],"ix":1},"s":{"a":0,"k":[100,100,100],"ix":6}},"ao":0,"shapes":[{"ty":"gr","it":[{"ind":0,"ty":"sh","ix":1,"ks":{"a":0,"k":{"i":[[0,0],[0,0]],"o":[[0,0],[0,0]],"v":[[-244.972,-128.429],[244.972,128.429]],"c":false},"ix":2},"nm":"Path 1","mn":"ADBE Vector Shape - Group","hd":false},{"ty":"st","c":{"a":0,"k":[0.361000001197,0.361000001197,0.426999978458,1],"ix":3},"o":{"a":0,"k":100,"ix":4},"w":{"a":0,"k":0.5,"ix":5},"lc":1,"lj":1,"ml":10,"bm":0,"nm":"Stroke 1","mn":"ADBE Vector Graphic - Stroke","hd":false},{"ty":"tr","p":{"a":0,"k":[245.222,128.679],"ix":2},"a":{"a":0,"k":[0,0],"ix":1},"s":{"a":0,"k":[100,100],"ix":3},"r":{"a":0,"k":0,"ix":6},"o":{"a":0,"k":100,"ix":7},"sk":{"a":0,"k":0,"ix":4},"sa":{"a":0,"k":0,"ix":5},"nm":"Transform"}],"nm":"Group 1","np":2,"cix":2,"bm":0,"ix":1,"mn":"ADBE Vector Group","hd":false}],"ip":0,"op":1200,"st":0,"bm":0},{"ddd":0,"ind":55,"ty":4,"nm":"Layer 58 Outlines","sr":1,"ks":{"o":{"a":0,"k":100,"ix":11},"r":{"a":0,"k":0,"ix":10},"p":{"a":0,"k":[1093.979,612.078,0],"ix":2},"a":{"a":0,"k":[12.739,6.691,0],"ix":1},"s":{"a":0,"k":[100,100,100],"ix":6}},"ao":0,"shapes":[{"ty":"gr","it":[{"ind":0,"ty":"sh","ix":1,"ks":{"a":0,"k":{"i":[[0,0],[0,0]],"o":[[0,0],[0,0]],"v":[[12.49,6.441],[-12.49,-6.441]],"c":false},"ix":2},"nm":"Path 1","mn":"ADBE Vector Shape - Group","hd":false},{"ty":"st","c":{"a":0,"k":[0.361000001197,0.361000001197,0.426999978458,1],"ix":3},"o":{"a":0,"k":100,"ix":4},"w":{"a":0,"k":0.5,"ix":5},"lc":1,"lj":1,"ml":10,"bm":0,"nm":"Stroke 1","mn":"ADBE Vector Graphic - Stroke","hd":false},{"ty":"tr","p":{"a":0,"k":[12.739,6.691],"ix":2},"a":{"a":0,"k":[0,0],"ix":1},"s":{"a":0,"k":[100,100],"ix":3},"r":{"a":0,"k":0,"ix":6},"o":{"a":0,"k":100,"ix":7},"sk":{"a":0,"k":0,"ix":4},"sa":{"a":0,"k":0,"ix":5},"nm":"Transform"}],"nm":"Group 1","np":2,"cix":2,"bm":0,"ix":1,"mn":"ADBE Vector Group","hd":false}],"ip":0,"op":1200,"st":0,"bm":0},{"ddd":0,"ind":56,"ty":4,"nm":"Layer 59 Outlines","sr":1,"ks":{"o":{"a":0,"k":100,"ix":11},"r":{"a":0,"k":0,"ix":10},"p":{"a":0,"k":[888.998,597.782,0],"ix":2},"a":{"a":0,"k":[12.211,3.318,0],"ix":1},"s":{"a":0,"k":[100,100,100],"ix":6}},"ao":0,"shapes":[{"ty":"gr","it":[{"ind":0,"ty":"sh","ix":1,"ks":{"a":0,"k":{"i":[[0,0],[0,0]],"o":[[0,0],[0,0]],"v":[[-11.961,3.068],[11.961,-3.068]],"c":false},"ix":2},"nm":"Path 1","mn":"ADBE Vector Shape - Group","hd":false},{"ty":"st","c":{"a":0,"k":[0.361000001197,0.361000001197,0.426999978458,1],"ix":3},"o":{"a":0,"k":100,"ix":4},"w":{"a":0,"k":0.5,"ix":5},"lc":1,"lj":1,"ml":10,"bm":0,"nm":"Stroke 1","mn":"ADBE Vector Graphic - Stroke","hd":false},{"ty":"tr","p":{"a":0,"k":[12.211,3.318],"ix":2},"a":{"a":0,"k":[0,0],"ix":1},"s":{"a":0,"k":[100,100],"ix":3},"r":{"a":0,"k":0,"ix":6},"o":{"a":0,"k":100,"ix":7},"sk":{"a":0,"k":0,"ix":4},"sa":{"a":0,"k":0,"ix":5},"nm":"Transform"}],"nm":"Group 1","np":2,"cix":2,"bm":0,"ix":1,"mn":"ADBE Vector Group","hd":false}],"ip":0,"op":1200,"st":0,"bm":0},{"ddd":0,"ind":57,"ty":4,"nm":"Layer 60 Outlines","sr":1,"ks":{"o":{"a":0,"k":100,"ix":11},"r":{"a":0,"k":0,"ix":10},"p":{"a":0,"k":[1044.731,642.185,0],"ix":2},"a":{"a":0,"k":[62.988,24.916,0],"ix":1},"s":{"a":0,"k":[100,100,100],"ix":6}},"ao":0,"shapes":[{"ty":"gr","it":[{"ind":0,"ty":"sh","ix":1,"ks":{"a":0,"k":{"i":[[0,0],[0,0],[0,0],[0,0]],"o":[[0,0],[0,0],[0,0],[0,0]],"v":[[-61.738,18.013],[61.738,-23.666],[61.738,-20.588],[-61.738,23.666]],"c":false},"ix":2},"nm":"Path 1","mn":"ADBE Vector Shape - Group","hd":false},{"ty":"st","c":{"a":0,"k":[0.361000001197,0.361000001197,0.426999978458,1],"ix":3},"o":{"a":0,"k":100,"ix":4},"w":{"a":0,"k":0.5,"ix":5},"lc":1,"lj":1,"ml":10,"bm":0,"nm":"Stroke 1","mn":"ADBE Vector Graphic - Stroke","hd":false},{"ty":"tr","p":{"a":0,"k":[62.988,24.916],"ix":2},"a":{"a":0,"k":[0,0],"ix":1},"s":{"a":0,"k":[100,100],"ix":3},"r":{"a":0,"k":0,"ix":6},"o":{"a":0,"k":100,"ix":7},"sk":{"a":0,"k":0,"ix":4},"sa":{"a":0,"k":0,"ix":5},"nm":"Transform"}],"nm":"Group 1","np":2,"cix":2,"bm":0,"ix":1,"mn":"ADBE Vector Group","hd":false}],"ip":0,"op":1200,"st":0,"bm":0},{"ddd":0,"ind":58,"ty":4,"nm":"Layer 61 Outlines","sr":1,"ks":{"o":{"a":0,"k":100,"ix":11},"r":{"a":0,"k":0,"ix":10},"p":{"a":0,"k":[930.015,633.351,0],"ix":2},"a":{"a":0,"k":[54.229,33.751,0],"ix":1},"s":{"a":0,"k":[100,100,100],"ix":6}},"ao":0,"shapes":[{"ty":"gr","it":[{"ind":0,"ty":"sh","ix":1,"ks":{"a":0,"k":{"i":[[0,0],[0,0],[0,0]],"o":[[0,0],[0,0],[0,0]],"v":[[52.979,32.501],[52.979,26.848],[-52.979,-32.501]],"c":false},"ix":2},"nm":"Path 1","mn":"ADBE Vector Shape - Group","hd":false},{"ty":"st","c":{"a":0,"k":[0.361000001197,0.361000001197,0.426999978458,1],"ix":3},"o":{"a":0,"k":100,"ix":4},"w":{"a":0,"k":0.5,"ix":5},"lc":1,"lj":1,"ml":10,"bm":0,"nm":"Stroke 1","mn":"ADBE Vector Graphic - Stroke","hd":false},{"ty":"tr","p":{"a":0,"k":[54.229,33.751],"ix":2},"a":{"a":0,"k":[0,0],"ix":1},"s":{"a":0,"k":[100,100],"ix":3},"r":{"a":0,"k":0,"ix":6},"o":{"a":0,"k":100,"ix":7},"sk":{"a":0,"k":0,"ix":4},"sa":{"a":0,"k":0,"ix":5},"nm":"Transform"}],"nm":"Group 1","np":2,"cix":2,"bm":0,"ix":1,"mn":"ADBE Vector Group","hd":false}],"ip":0,"op":1200,"st":0,"bm":0},{"ddd":0,"ind":59,"ty":4,"nm":"Layer 62 Outlines","sr":1,"ks":{"o":{"a":0,"k":100,"ix":11},"r":{"a":0,"k":0,"ix":10},"p":{"a":0,"k":[488.648,340.94,0],"ix":2},"a":{"a":0,"k":[281.674,152.954,0],"ix":1},"s":{"a":0,"k":[100,100,100],"ix":6}},"ao":0,"shapes":[{"ty":"gr","it":[{"ind":0,"ty":"sh","ix":1,"ks":{"a":0,"k":{"i":[[0,0],[0,0]],"o":[[0,0],[0,0]],"v":[[279.674,150.954],[-279.674,-150.953]],"c":false},"ix":2},"nm":"Path 1","mn":"ADBE Vector Shape - Group","hd":false},{"ty":"st","c":{"a":0,"k":[0.361000001197,0.361000001197,0.426999978458,1],"ix":3},"o":{"a":0,"k":100,"ix":4},"w":{"a":0,"k":4,"ix":5},"lc":1,"lj":1,"ml":10,"bm":0,"nm":"Stroke 1","mn":"ADBE Vector Graphic - Stroke","hd":false},{"ty":"tr","p":{"a":0,"k":[281.674,152.953],"ix":2},"a":{"a":0,"k":[0,0],"ix":1},"s":{"a":0,"k":[100,100],"ix":3},"r":{"a":0,"k":0,"ix":6},"o":{"a":0,"k":100,"ix":7},"sk":{"a":0,"k":0,"ix":4},"sa":{"a":0,"k":0,"ix":5},"nm":"Transform"}],"nm":"Group 1","np":2,"cix":2,"bm":0,"ix":1,"mn":"ADBE Vector Group","hd":false}],"ip":0,"op":1200,"st":0,"bm":0}]}],"fonts":{"list":[{"fName":"PTRootUIWeb-Light","fFamily":"PT Root UI Web","fStyle":"Light","ascent":69.9996948242188}]},"layers":[{"ddd":0,"ind":1,"ty":5,"nm":"On 2","sr":1,"ks":{"o":{"a":1,"k":[{"i":{"x":[0.833],"y":[0.833]},"o":{"x":[0.167],"y":[0.167]},"t":271,"s":[0]},{"i":{"x":[0.833],"y":[0.833]},"o":{"x":[0.167],"y":[0.167]},"t":281,"s":[100]},{"i":{"x":[0.833],"y":[0.833]},"o":{"x":[0.167],"y":[0.167]},"t":430,"s":[100]},{"t":438,"s":[0]}],"ix":11},"r":{"a":0,"k":0,"ix":10},"p":{"a":0,"k":[374,467,0],"ix":2},"a":{"a":0,"k":[0,0,0],"ix":1},"s":{"a":0,"k":[100,100,100],"ix":6}},"ao":0,"t":{"d":{"k":[{"s":{"s":36,"f":"PTRootUIWeb-Light","t":"On","j":2,"tr":0,"lh":43.2,"ls":0,"fc":[0,0.337,1]},"t":0}]},"p":{},"m":{"g":1,"a":{"a":0,"k":[0,0],"ix":2}},"a":[]},"ip":40,"op":1240,"st":40,"bm":0},{"ddd":0,"ind":2,"ty":5,"nm":"Off 2","sr":1,"ks":{"o":{"a":1,"k":[{"i":{"x":[0.833],"y":[0.833]},"o":{"x":[0.167],"y":[0.167]},"t":40,"s":[0]},{"i":{"x":[0.833],"y":[0.833]},"o":{"x":[0.167],"y":[0.167]},"t":50,"s":[100]},{"i":{"x":[0.833],"y":[0.833]},"o":{"x":[0.167],"y":[0.167]},"t":198,"s":[100]},{"t":206,"s":[0]}],"ix":11},"r":{"a":0,"k":0,"ix":10},"p":{"a":0,"k":[374,467,0],"ix":2},"a":{"a":0,"k":[0,0,0],"ix":1},"s":{"a":0,"k":[100,100,100],"ix":6}},"ao":0,"t":{"d":{"k":[{"s":{"s":36,"f":"PTRootUIWeb-Light","t":"Off","j":2,"tr":0,"lh":43.2,"ls":0,"fc":[0.867,0,0.867]},"t":0}]},"p":{},"m":{"g":1,"a":{"a":0,"k":[0,0],"ix":2}},"a":[]},"ip":40,"op":1240,"st":40,"bm":0},{"ddd":0,"ind":3,"ty":5,"nm":"12","sr":1,"ks":{"o":{"a":1,"k":[{"i":{"x":[0.833],"y":[0.833]},"o":{"x":[0.167],"y":[0.167]},"t":392,"s":[0]},{"i":{"x":[0.833],"y":[0.833]},"o":{"x":[0.167],"y":[0.167]},"t":402,"s":[100]},{"i":{"x":[0.833],"y":[0.833]},"o":{"x":[0.167],"y":[0.167]},"t":430,"s":[100]},{"t":438,"s":[0]}],"ix":11},"r":{"a":0,"k":0,"ix":10},"p":{"a":0,"k":[428.76,463.124,0],"ix":2},"a":{"a":0,"k":[-0.24,-14.876,0],"ix":1},"s":{"a":0,"k":[100,100,100],"ix":6}},"ao":0,"t":{"d":{"k":[{"s":{"s":72,"f":"PTRootUIWeb-Light","t":"3","j":2,"tr":0,"lh":86.4,"ls":0,"fc":[0.393,0.393,0.471]},"t":0}]},"p":{},"m":{"g":1,"a":{"a":0,"k":[0,0],"ix":2}},"a":[]},"ip":392,"op":452,"st":392,"bm":0},{"ddd":0,"ind":4,"ty":5,"nm":"11","sr":1,"ks":{"o":{"a":1,"k":[{"i":{"x":[0.833],"y":[0.833]},"o":{"x":[0.167],"y":[0.167]},"t":332,"s":[0]},{"i":{"x":[0.833],"y":[0.833]},"o":{"x":[0.167],"y":[0.167]},"t":342,"s":[100]},{"i":{"x":[0.833],"y":[0.833]},"o":{"x":[0.167],"y":[0.167]},"t":384,"s":[100]},{"t":392,"s":[0]}],"ix":11},"r":{"a":0,"k":0,"ix":10},"p":{"a":0,"k":[428.76,463.124,0],"ix":2},"a":{"a":0,"k":[-0.24,-14.876,0],"ix":1},"s":{"a":0,"k":[100,100,100],"ix":6}},"ao":0,"t":{"d":{"k":[{"s":{"s":72,"f":"PTRootUIWeb-Light","t":"2","j":2,"tr":0,"lh":86.4,"ls":0,"fc":[0.393,0.393,0.471]},"t":0}]},"p":{},"m":{"g":1,"a":{"a":0,"k":[0,0],"ix":2}},"a":[]},"ip":332,"op":392,"st":332,"bm":0},{"ddd":0,"ind":5,"ty":5,"nm":"10","sr":1,"ks":{"o":{"a":1,"k":[{"i":{"x":[0.833],"y":[0.833]},"o":{"x":[0.167],"y":[0.167]},"t":271,"s":[0]},{"i":{"x":[0.833],"y":[0.833]},"o":{"x":[0.167],"y":[0.167]},"t":281,"s":[100]},{"i":{"x":[0.833],"y":[0.833]},"o":{"x":[0.167],"y":[0.167]},"t":323,"s":[100]},{"t":331,"s":[0]}],"ix":11},"r":{"a":0,"k":0,"ix":10},"p":{"a":0,"k":[428.76,463.124,0],"ix":2},"a":{"a":0,"k":[-0.24,-14.876,0],"ix":1},"s":{"a":0,"k":[100,100,100],"ix":6}},"ao":0,"t":{"d":{"k":[{"s":{"s":72,"f":"PTRootUIWeb-Light","t":"1","j":2,"tr":0,"lh":86.4,"ls":0,"fc":[0.393,0.393,0.471]},"t":0}]},"p":{},"m":{"g":1,"a":{"a":0,"k":[0,0],"ix":2}},"a":[]},"ip":271,"op":332,"st":271,"bm":0},{"ddd":0,"ind":6,"ty":5,"nm":"9","sr":1,"ks":{"o":{"a":1,"k":[{"i":{"x":[0.833],"y":[0.833]},"o":{"x":[0.167],"y":[0.167]},"t":161,"s":[0]},{"i":{"x":[0.833],"y":[0.833]},"o":{"x":[0.167],"y":[0.167]},"t":171,"s":[100]},{"i":{"x":[0.833],"y":[0.833]},"o":{"x":[0.167],"y":[0.167]},"t":199,"s":[100]},{"t":207,"s":[0]}],"ix":11},"r":{"a":0,"k":0,"ix":10},"p":{"a":0,"k":[428.76,463.124,0],"ix":2},"a":{"a":0,"k":[-0.24,-14.876,0],"ix":1},"s":{"a":0,"k":[100,100,100],"ix":6}},"ao":0,"t":{"d":{"k":[{"s":{"s":72,"f":"PTRootUIWeb-Light","t":"3","j":2,"tr":0,"lh":86.4,"ls":0,"fc":[0.393,0.393,0.471]},"t":0}]},"p":{},"m":{"g":1,"a":{"a":0,"k":[0,0],"ix":2}},"a":[]},"ip":161,"op":221,"st":161,"bm":0},{"ddd":0,"ind":7,"ty":5,"nm":"8","sr":1,"ks":{"o":{"a":1,"k":[{"i":{"x":[0.833],"y":[0.833]},"o":{"x":[0.167],"y":[0.167]},"t":101,"s":[0]},{"i":{"x":[0.833],"y":[0.833]},"o":{"x":[0.167],"y":[0.167]},"t":111,"s":[100]},{"i":{"x":[0.833],"y":[0.833]},"o":{"x":[0.167],"y":[0.167]},"t":153,"s":[100]},{"t":161,"s":[0]}],"ix":11},"r":{"a":0,"k":0,"ix":10},"p":{"a":0,"k":[428.76,463.124,0],"ix":2},"a":{"a":0,"k":[-0.24,-14.876,0],"ix":1},"s":{"a":0,"k":[100,100,100],"ix":6}},"ao":0,"t":{"d":{"k":[{"s":{"s":72,"f":"PTRootUIWeb-Light","t":"2","j":2,"tr":0,"lh":86.4,"ls":0,"fc":[0.393,0.393,0.471]},"t":0}]},"p":{},"m":{"g":1,"a":{"a":0,"k":[0,0],"ix":2}},"a":[]},"ip":101,"op":161,"st":101,"bm":0},{"ddd":0,"ind":8,"ty":5,"nm":"7","sr":1,"ks":{"o":{"a":1,"k":[{"i":{"x":[0.833],"y":[0.833]},"o":{"x":[0.167],"y":[0.167]},"t":40,"s":[0]},{"i":{"x":[0.833],"y":[0.833]},"o":{"x":[0.167],"y":[0.167]},"t":50,"s":[100]},{"i":{"x":[0.833],"y":[0.833]},"o":{"x":[0.167],"y":[0.167]},"t":92,"s":[100]},{"t":100,"s":[0]}],"ix":11},"r":{"a":0,"k":0,"ix":10},"p":{"a":0,"k":[428.76,463.124,0],"ix":2},"a":{"a":0,"k":[-0.24,-14.876,0],"ix":1},"s":{"a":0,"k":[100,100,100],"ix":6}},"ao":0,"t":{"d":{"k":[{"s":{"s":72,"f":"PTRootUIWeb-Light","t":"1","j":2,"tr":0,"lh":86.4,"ls":0,"fc":[0.393,0.393,0.471]},"t":0}]},"p":{},"m":{"g":1,"a":{"a":0,"k":[0,0],"ix":2}},"a":[]},"ip":40,"op":101,"st":40,"bm":0},{"ddd":0,"ind":9,"ty":4,"nm":"Shape Layer 2","td":1,"sr":1,"ks":{"o":{"a":0,"k":100,"ix":11},"r":{"a":0,"k":0,"ix":10},"p":{"a":0,"k":[428,357.111,0],"ix":2},"a":{"a":0,"k":[-86.096,164.111,0],"ix":1},"s":{"a":0,"k":[100,100,100],"ix":6}},"ao":0,"shapes":[{"ty":"gr","it":[{"d":1,"ty":"el","s":{"a":0,"k":[654.348,654.348],"ix":2},"p":{"a":0,"k":[0,0],"ix":3},"nm":"Ellipse Path 1","mn":"ADBE Vector Shape - Ellipse","hd":false},{"ty":"gf","o":{"a":0,"k":100,"ix":10},"r":1,"bm":0,"g":{"p":3,"k":{"a":0,"k":[0,0,0,0,0.537,0,0,0,1,0,0,0,0,1,0.15,1,0.3,1,0.65,0.5,1,0],"ix":9}},"s":{"a":0,"k":[0,0],"ix":5},"e":{"a":0,"k":[329.391,0],"ix":6},"t":2,"h":{"a":0,"k":0,"ix":7},"a":{"a":0,"k":0,"ix":8},"nm":"Gradient Fill 1","mn":"ADBE Vector Graphic - G-Fill","hd":false},{"ty":"tr","p":{"a":0,"k":[-86.096,164.111],"ix":2},"a":{"a":0,"k":[0,0],"ix":1},"s":{"a":0,"k":[130.392,130.392],"ix":3},"r":{"a":0,"k":0,"ix":6},"o":{"a":0,"k":100,"ix":7},"sk":{"a":0,"k":0,"ix":4},"sa":{"a":0,"k":0,"ix":5},"nm":"Transform"}],"nm":"Ellipse 1","np":3,"cix":2,"bm":0,"ix":1,"mn":"ADBE Vector Group","hd":false}],"ip":0,"op":1200,"st":0,"bm":0},{"ddd":0,"ind":10,"ty":0,"nm":"jammy e_in","tt":1,"refId":"comp_0","sr":1,"ks":{"o":{"a":0,"k":100,"ix":11},"r":{"a":0,"k":0,"ix":10},"p":{"a":0,"k":[482,231,0],"ix":2},"a":{"a":0,"k":[960,540,0],"ix":1},"s":{"a":0,"k":[100,100,100],"ix":6}},"ao":0,"w":1920,"h":1080,"ip":0,"op":1200,"st":0,"bm":0}],"markers":[],"chars":[{"ch":"1","size":72,"style":"Light","w":35,"data":{"shapes":[{"ty":"gr","it":[{"ind":0,"ty":"sh","ix":1,"ks":{"a":0,"k":{"i":[[0,0],[0,0],[0,0],[0,0],[0,0],[0,0],[0,0]],"o":[[0,0],[0,0],[0,0],[0,0],[0,0],[0,0],[0,0]],"v":[[4,-54.4],[19.4,-64.7],[19.4,0],[24,0],[24,-70],[19.4,-70],[4,-59.6]],"c":true},"ix":2},"nm":"1","mn":"ADBE Vector Shape - Group","hd":false}],"nm":"1","np":3,"cix":2,"bm":0,"ix":1,"mn":"ADBE Vector Group","hd":false}]},"fFamily":"PT Root UI Web"},{"ch":"2","size":72,"style":"Light","w":55,"data":{"shapes":[{"ty":"gr","it":[{"ind":0,"ty":"sh","ix":1,"ks":{"a":0,"k":{"i":[[0,0],[0,0],[0,0],[0,0],[0,0],[-1.767,2],[-1.2,1.9],[-0.634,1.9],[0,2.2],[1.033,2.334],[1.9,1.734],[2.633,1],[3.2,0],[2.633,-1],[1.9,-1.733],[1.033,-2.333],[0,-2.6],[0,0],[-0.834,1.734],[-1.467,1.334],[-2.034,0.767],[-2.467,0],[-2.067,-0.766],[-1.467,-1.333],[-0.8,-1.733],[0,-2],[0.533,-1.633],[1.033,-1.666],[1.6,-1.766],[2.2,-2.2],[0,0]],"o":[[0,0],[0,0],[0,0],[0,0],[2.266,-2.266],[1.766,-2],[1.2,-1.9],[0.633,-1.9],[0,-2.6],[-1.034,-2.333],[-1.9,-1.733],[-2.634,-1],[-3.2,0],[-2.634,1],[-1.9,1.734],[-1.034,2.334],[0,0],[0,-2],[0.833,-1.733],[1.466,-1.333],[2.033,-0.766],[2.466,0],[2.066,0.767],[1.466,1.334],[0.8,1.734],[0,1.867],[-0.534,1.634],[-1.034,1.667],[-1.6,1.767],[0,0],[0,0]],"v":[[5,0],[49,0],[49,-4.4],[11.1,-4.4],[34.3,-27.4],[40.35,-33.8],[44.8,-39.65],[47.55,-45.35],[48.5,-51.5],[46.95,-58.9],[42.55,-65],[35.75,-69.1],[27,-70.6],[18.25,-69.1],[11.45,-65],[7.05,-58.9],[5.5,-51.5],[10.3,-51.5],[11.55,-57.1],[15,-61.7],[20.25,-64.85],[27,-66],[33.8,-64.85],[39.1,-61.7],[42.5,-57.1],[43.7,-51.5],[42.9,-46.25],[40.55,-41.3],[36.6,-36.15],[30.9,-30.2],[5,-4.4]],"c":true},"ix":2},"nm":"2","mn":"ADBE Vector Shape - Group","hd":false}],"nm":"2","np":3,"cix":2,"bm":0,"ix":1,"mn":"ADBE Vector Group","hd":false}]},"fFamily":"PT Root UI Web"},{"ch":"3","size":72,"style":"Light","w":58,"data":{"shapes":[{"ty":"gr","it":[{"ind":0,"ty":"sh","ix":1,"ks":{"a":0,"k":{"i":[[-2.734,0.966],[-1.867,1.734],[-1,2.4],[0,2.867],[2.166,3.034],[3.933,1.334],[-1.934,2.834],[0,3.6],[0.933,2.267],[1.733,1.634],[2.566,0.9],[3.2,0],[2.5,-0.933],[1.8,-1.7],[1.066,-2.333],[0.2,-2.8],[0,0],[-0.867,1.8],[-1.4,1.3],[-1.867,0.734],[-2.334,0],[-2.734,-2.566],[0,-4.266],[0.733,-1.7],[1.3,-1.233],[1.8,-0.733],[2.133,0],[0,0],[0,0],[0,0],[-2,-0.733],[-1.4,-1.333],[-0.767,-1.833],[0,-2.133],[2.966,-2.8],[5.533,0],[3.033,2.967],[0.333,5.2],[0,0],[-3.867,-3.8],[-6.534,0]],"o":[[2.733,-0.966],[1.866,-1.733],[1,-2.4],[0,-4],[-2.167,-3.033],[3.4,-1.4],[1.933,-2.833],[0,-2.733],[-0.934,-2.266],[-1.734,-1.633],[-2.567,-0.9],[-3.067,0],[-2.5,0.934],[-1.8,1.7],[-1.067,2.334],[0,0],[0.2,-2.133],[0.866,-1.8],[1.4,-1.3],[1.866,-0.733],[5,0],[2.733,2.567],[0,2],[-0.734,1.7],[-1.3,1.234],[-1.8,0.734],[0,0],[0,0],[0,0],[2.466,0],[2,0.734],[1.4,1.334],[0.766,1.834],[0,4.534],[-2.967,2.8],[-5.067,0],[-3.034,-2.966],[0,0],[0.4,6.467],[3.866,3.8],[3.466,0]],"v":[[37.8,-0.85],[44.7,-4.9],[49,-11.1],[50.5,-19],[47.25,-29.55],[38.1,-36.1],[46.1,-42.45],[49,-52.1],[47.6,-59.6],[43.6,-65.45],[37.15,-69.25],[28.5,-70.6],[20.15,-69.2],[13.7,-65.25],[9.4,-59.2],[7.5,-51.5],[12.3,-51.5],[13.9,-57.4],[17.3,-62.05],[22.2,-65.1],[28.5,-66.2],[40.1,-62.35],[44.2,-52.1],[43.1,-46.55],[40.05,-42.15],[35.4,-39.2],[29.5,-38.1],[20,-38.1],[20,-33.9],[29.5,-33.9],[36.2,-32.8],[41.3,-29.7],[44.55,-24.95],[45.7,-19],[41.25,-8],[28.5,-3.8],[16.35,-8.25],[11.3,-20.5],[6.5,-20.5],[12.9,-5.1],[28.5,0.6]],"c":true},"ix":2},"nm":"3","mn":"ADBE Vector Shape - Group","hd":false}],"nm":"3","np":3,"cix":2,"bm":0,"ix":1,"mn":"ADBE Vector Group","hd":false}]},"fFamily":"PT Root UI Web"},{"ch":"O","size":36,"style":"Light","w":71,"data":{"shapes":[{"ty":"gr","it":[{"ind":0,"ty":"sh","ix":1,"ks":{"a":0,"k":{"i":[[-3.434,1.467],[-2.5,2.767],[-1.434,3.967],[0,5],[0,0],[1.433,3.967],[2.5,2.767],[3.4,1.467],[4,0],[3.433,-1.466],[2.5,-2.766],[1.433,-3.966],[0,-5],[0,0],[-1.434,-3.966],[-2.5,-2.766],[-3.4,-1.466],[-4,0]],"o":[[3.433,-1.466],[2.5,-2.766],[1.433,-3.966],[0,0],[0,-5],[-1.434,-3.966],[-2.5,-2.766],[-3.4,-1.466],[-3.934,0],[-3.434,1.467],[-2.5,2.767],[-1.434,3.967],[0,0],[0,5],[1.433,3.967],[2.5,2.767],[3.4,1.467],[3.933,0]],"v":[[46.55,-1.6],[55.45,-7.95],[61.35,-18.05],[63.5,-31.5],[63.5,-38.5],[61.35,-51.95],[55.45,-62.05],[46.6,-68.4],[35.5,-70.6],[24.45,-68.4],[15.55,-62.05],[9.65,-51.95],[7.5,-38.5],[7.5,-31.5],[9.65,-18.05],[15.55,-7.95],[24.4,-1.6],[35.5,0.6]],"c":true},"ix":2},"nm":"O","mn":"ADBE Vector Shape - Group","hd":false},{"ind":1,"ty":"sh","ix":2,"ks":{"a":0,"k":{"i":[[2.833,1.267],[2.1,2.367],[1.2,3.434],[0,4.334],[0,0],[-1.2,3.434],[-2.1,2.367],[-2.8,1.234],[-3.267,0],[-2.834,-1.266],[-2.1,-2.366],[-1.2,-3.433],[0,-4.333],[0,0],[1.2,-3.433],[2.1,-2.366],[2.8,-1.233],[3.266,0]],"o":[[-2.834,-1.266],[-2.1,-2.366],[-1.2,-3.433],[0,0],[0,-4.4],[1.2,-3.433],[2.1,-2.366],[2.8,-1.233],[3.2,0],[2.833,1.267],[2.1,2.367],[1.2,3.434],[0,0],[0,4.4],[-1.2,3.434],[-2.1,2.367],[-2.8,1.234],[-3.2,0]],"v":[[26.45,-5.7],[19.05,-11.15],[14.1,-19.85],[12.3,-31.5],[12.3,-38.5],[14.1,-50.25],[19.05,-58.95],[26.4,-64.35],[35.5,-66.2],[44.55,-64.3],[51.95,-58.85],[56.9,-50.15],[58.7,-38.5],[58.7,-31.5],[56.9,-19.75],[51.95,-11.05],[44.6,-5.65],[35.5,-3.8]],"c":true},"ix":2},"nm":"O","mn":"ADBE Vector Shape - Group","hd":false}],"nm":"O","np":5,"cix":2,"bm":0,"ix":1,"mn":"ADBE Vector Group","hd":false}]},"fFamily":"PT Root UI Web"},{"ch":"f","size":36,"style":"Light","w":36.5,"data":{"shapes":[{"ty":"gr","it":[{"ind":0,"ty":"sh","ix":1,"ks":{"a":0,"k":{"i":[[0,0],[0,0],[0,0],[0,0],[0,0],[0,0],[0,0],[0,0],[0,0],[-1.3,1.3],[-2.8,0],[0,0],[0,0],[0,0],[0,-8],[0,0],[0,0]],"o":[[0,0],[0,0],[0,0],[0,0],[0,0],[0,0],[0,0],[0,0],[0,-2.933],[1.3,-1.3],[0,0],[0,0],[0,0],[-8,0],[0,0],[0,0],[0,0]],"v":[[4,-46],[13,-46],[13,0],[17.4,0],[17.4,-46],[30,-46],[30,-50],[17.4,-50],[17.4,-57.5],[19.35,-63.85],[25.5,-65.8],[32,-65.8],[32,-70],[25,-70],[13,-58],[13,-50],[4,-50]],"c":true},"ix":2},"nm":"f","mn":"ADBE Vector Shape - Group","hd":false}],"nm":"f","np":3,"cix":2,"bm":0,"ix":1,"mn":"ADBE Vector Group","hd":false}]},"fFamily":"PT Root UI Web"},{"ch":"n","size":36,"style":"Light","w":57.5,"data":{"shapes":[{"ty":"gr","it":[{"ind":0,"ty":"sh","ix":1,"ks":{"a":0,"k":{"i":[[0,0],[0,0],[0,0],[-0.834,1.867],[-1.4,1.367],[-1.934,0.734],[-2.334,0],[-2.5,-2.633],[0,-5.333],[0,0],[0,0],[0,0],[3.2,3.367],[5.6,0],[2.9,-1.6],[1.666,-2.933],[0,0],[0,0]],"o":[[0,0],[0,0],[0.066,-2.2],[0.833,-1.866],[1.4,-1.366],[1.933,-0.733],[4.4,0],[2.5,2.634],[0,0],[0,0],[0,0],[0,-6.666],[-3.2,-3.366],[-3.867,0],[-2.9,1.6],[0,0],[0,0],[0,0]],"v":[[9.5,0],[13.9,0],[13.9,-31.2],[15.25,-37.3],[18.6,-42.15],[23.6,-45.3],[30,-46.4],[40.35,-42.45],[44.1,-30.5],[44.1,0],[48.5,0],[48.5,-30.5],[43.7,-45.55],[30.5,-50.6],[20.35,-48.2],[13.5,-41.4],[13.1,-50],[9.5,-50]],"c":true},"ix":2},"nm":"n","mn":"ADBE Vector Shape - Group","hd":false}],"nm":"n","np":3,"cix":2,"bm":0,"ix":1,"mn":"ADBE Vector Group","hd":false}]},"fFamily":"PT Root UI Web"}]}